Workbook

Sheet Extração
A1: LLM1: CHATGPT
A2: LLM2: GEMINI
A3: ID do artigo | B3: Tipo de publicação | C3: Local de publicação | D3: Título | E3: Link | F3: Ano | G3: Autores | H3: País | I3: Base de Dados | J3: RQ (Pergunta de Pesquisa) | K3: Extração LLM 1 (ChatGPT) | L3: Extração LLM 2 (Gemini) | M3: Extração validada (humana) | N3: ChatGPT acertou? | O3: Gemini acertou? | P3: Concordância entre LLMs | Q3: Observações / Comentários
A4: 2 | C4: <<nome da conferência ou periódico>> | D4: Exploiting Blockchain to Make AI Trustworthy: A Software Development Lifecycle View | E4: Exploiting Blockchain to Make AI Trustworthy: A Software Development Lifecycle View | ACM Computing Surveys | F4: 2024 | G4: Peiyun Zhang, Song Ding, Qinglin Zhao | I4: ACM | J4: RQ1 | K4: <<Texto extraído da IA>> | L4: <<Texto extraído da IA>> | P4: =IF(OR(N4="",O4=""),"",IF(N4=O4,"Igual","Diferente"))
A5: 2 | C5: <<nome da conferência ou periódico>> | D5: Exploiting Blockchain to Make AI Trustworthy: A Software Development Lifecycle View | E5: Exploiting Blockchain to Make AI Trustworthy: A Software Development Lifecycle View | ACM Computing Surveys | F5: 2024 | G5: Peiyun Zhang, Song Ding, Qinglin Zhao | I5: ACM | J5: RQ2 | K5: <<Texto extraído da IA>> | L5: <<Texto extraído da IA>> | P5: =IF(OR(N5="",O5=""),"",IF(N5=O5,"Igual","Diferente"))
A6: 2 | C6: <<nome da conferência ou periódico>> | D6: Exploiting Blockchain to Make AI Trustworthy: A Software Development Lifecycle View | E6: Exploiting Blockchain to Make AI Trustworthy: A Software Development Lifecycle View | ACM Computing Surveys | F6: 2024 | G6: Peiyun Zhang, Song Ding, Qinglin Zhao | I6: ACM | J6: RQ3 | K6: <<Texto extraído da IA>> | L6: <<Texto extraído da IA>> | P6: =IF(OR(N6="",O6=""),"",IF(N6=O6,"Igual","Diferente"))
A7: 2 | C7: <<nome da conferência ou periódico>> | D7: Exploiting Blockchain to Make AI Trustworthy: A Software Development Lifecycle View | E7: Exploiting Blockchain to Make AI Trustworthy: A Software Development Lifecycle View | ACM Computing Surveys | F7: 2024 | G7: Peiyun Zhang, Song Ding, Qinglin Zhao | I7: ACM | J7: RQ4 | K7: <<Texto extraído da IA>> | L7: <<Texto extraído da IA>> | P7: =IF(OR(N7="",O7=""),"",IF(N7=O7,"Igual","Diferente"))
A8: 7 | B8: Journal | C8: Estados Unidos | D8: A novel framework to identify cybersecurity challenges and opportunities for organizational digital transformation in the cloud | E8: https://doi.org/10.1016/j.cose.2025.104339 | F8: 2025 | G8: Xueping Liang, Yilin Xu | H8: Estados Unidos | I8: Science Direct | J8: RQ1 | K8: A IA é aplicada principalmente na segurança em nuvem por meio de machine learning e técnicas inteligentes para detecção de ameaças, prevenção de invasões, análise de padrões e suporte ao monitoramento de sistemas críticos. Os benefícios incluem maior capacidade de resposta, automação e mitigação proativa de riscos, enquanto os desafios abrangem privacidade, confiança, disponibilidade e complexidade regulatória. A governança envolve modelos como Zero Trust, auditorias, controle de acesso e conformidade com padrões legais. | L8: A IA e o Aprendizado de Máquina são integrados para automatizar a detecção de ameaças em tempo real e otimizar a análise de segurança, utilizando "Frameworks de Automação de Conformidade na Nuvem" para verificar alinhamento com normas como GDPR e HIPAA. A governança emerge através de arquiteturas Zero Trust e gerenciadores de políticas que auditam o acesso e a integridade dos dados, garantindo conformidade legal e reduzindo riscos financeiros. | M8: A IA (Machine Learning e Inteligência Artificial) está sendo integrada para melhorar a segurança na nuvem. O principal benefício é o potencial de detecção avançada de ameaças e resposta automatizada. O maior desafio é garantir a privacidade e proteção de dados, e a governança foca em aderir a diversas estruturas regulatórias como o GDPR e o HIPAA. | N8: Sim | O8: Sim | P8: =IF(OR(N8="",O8=""),"",IF(N8=O8,"Igual","Diferente")) -> Igual
A9: 7 | B9: Journal | C9: Estados Unidos | D9: A novel framework to identify cybersecurity challenges and opportunities for organizational digital transformation in the cloud | E9: https://doi.org/10.1016/j.cose.2025.104339 | F9: 2025 | G9: Xueping Liang, Yilin Xu | H9: Estados Unidos | I9: Science Direct | J9: RQ2 | K9: As técnicas de IA mais citadas incluem machine learning, algoritmos de detecção de anomalias, análise baseada em comportamento, métodos criptográficos inteligentes, sistemas de detecção de intrusão, autenticação multifatorial e modelos baseados em confiança. O artigo também destaca uso de blockchain, homomorphic encryption e frameworks de segurança orientados a dados. | L9: O estudo destaca o uso de Aprendizado de Máquina Supervisionado para simplificar processos de segurança e detectar ataques em tempo de execução, além de Deep Learning para processar grandes volumes de dados no setor de saúde. Também são empregadas análises comportamentais dentro de arquiteturas Zero Trust para identificar anomalias de uso e padrões de ameaças em ambientes de nuvem. | M9: O Machine Learning (ML) e a Inteligência Artificial (AI) são utilizados para detecção de ataques durante o runtime e para análise de comportamento em arquiteturas Zero Trust (ZTA). A IA também é importante para otimizar a análise de dados, sendo as PETs (Tecnologias de Aprimoramento da Privacidade) citadas como essenciais para garantir a privacidade dos dados pessoais. | N9: Sim | O9: Sim | P9: =IF(OR(N9="",O9=""),"",IF(N9=O9,"Igual","Diferente")) -> Igual
A10: 7 | B10: Journal | C10: Estados Unidos | D10: A novel framework to identify cybersecurity challenges and opportunities for organizational digital transformation in the cloud | E10: https://doi.org/10.1016/j.cose.2025.104339 | F10: 2025 | G10: Xueping Liang, Yilin Xu | H10: Estados Unidos | I10: Science Direct | J10: RQ3 | K10: Entre os benefícios estão maior segurança, redução de riscos, melhoria na tomada de decisão, detecção precoce de ataques e escalabilidade em ambientes de nuvem. Os principais desafios incluem vazamento de dados, acesso não autorizado, ataques cibernéticos, falta de padrões, complexidade das ameaças, privacidade, conformidade legal e requisitos de alta confiabilidade. | L10: Os benefícios incluem a detecção dinâmica de ataques, otimização da análise de dados e redução da complexidade do sistema, permitindo foco no refinamento de algoritmos. Os desafios envolvem a dependência de grandes conjuntos de dados, a necessidade de manter a qualidade das informações e a obrigação crítica de preservar a privacidade dos dados durante o processamento usando Tecnologias de Aprimoramento de Privacidade (PETs). | M10: Os benefícios incluem o desenvolvimento ágil de soluções, a otimização de custos e recursos, e a detecção mais eficaz de ameaças. Os desafios envolvem a privacidade e proteção de dados, a complexidade do gerenciamento de identidades e acesso (IAM), e os trade-offs entre segurança e desempenho. | N10: Sim | O10: Sim | P10: =IF(OR(N10="",O10=""),"",IF(N10=O10,"Igual","Diferente")) -> Igual
A11: 7 | B11: Journal | C11: Estados Unidos | D11: A novel framework to identify cybersecurity challenges and opportunities for organizational digital transformation in the cloud | E11: https://doi.org/10.1016/j.cose.2025.104339 | F11: 2025 | G11: Xueping Liang, Yilin Xu | H11: Estados Unidos | I11: Science Direct | J11: RQ4 | K11: Os estudos tratam governança e ética enfatizando privacidade, conformidade legal (incluindo GDPR como exemplo direto), auditorias, mecanismos de confiança, proteção de dados, modelos de compliance, controle de acesso, monitoramento e accountability. O artigo também destaca a importância de frameworks regulatórios, políticas internas e gestão de riscos em sistemas em nuvem. | L11: A governança é estruturada através de artefatos de Design Science focados em conformidade, como painéis de monitoramento que garantem adesão a leis como GDPR e HIPAA. A ética e a transparência são reforçadas pelo uso de Blockchain para proveniência imutável de dados e arquiteturas Zero Trust que eliminam a confiança implícita, exigindo verificação contínua de identidade e acesso. | M11: A governança exige a conformidade com regulamentações como o GDPR e o HIPAA. A ética é abordada pela exploração de modelos de aprendizado federado para aprimorar a privacidade e pelo uso da tecnologia Blockchain para garantir a imunidade e transparência no rastreamento da proveniência dos dados. A LGPD brasileira não é mencionada nas fontes. | N11: Sim | O11: Sim | P11: =IF(OR(N11="",O11=""),"",IF(N11=O11,"Igual","Diferente")) -> Igual
A12: 9 | B12: Journal | C12: França | D12: Privacy controls as an information source to reduce data poisoning in artificial intelligence-powered personalization | E12: https://doi.org/10.1016/j.jbusres.2022.07.045 | F12: 2022 | G12: Julien Cloarec | H12: França | I12: Science Direct | J12: RQ1 | K12: O artigo discute IA apenas como tecnologia de personalização, não como ferramenta de compliance. A IA aparece como contexto para explicar como vulnerabilidades e assimetria de poder levam consumidores a falsificar dados, e como controles de privacidade podem mitigar esse problema, mas não trata de estruturas de governança ou automação regulatória. | L12: O estudo não foca na aplicação de IA para automatizar a conformidade, mas sim na reação dos consumidores (falsificação de dados) à personalização alimentada por IA e marketing orientado a dados. A estrutura de governança discutida envolve o uso de controles de privacidade como fonte de informação para reduzir a vulnerabilidade do consumidor e o envenenamento de dados, equilibrando poder de mercado e ética digital. | M12: O artigo discute a aplicação da Inteligência Artificial no contexto da personalização orientada por dados, que aumenta a vulnerabilidade do consumidor e o leva à falsificação de informações. Embora o artigo mencione regulamentações de privacidade e a existência de paradoxos da IA nos mercados consumidores que trazem desafios éticos, ele não detalha especificamente como técnicas de machine learning ou PLN estão sendo usadas para automatizar e aprimorar a conformidade regulatória (RegTech), nem lista os principais benefícios ou as estruturas de governança dessa automação | N12: Sim | O12: Sim | P12: =IF(OR(N12="",O12=""),"",IF(N12=O12,"Igual","Diferente")) -> Igual
A13: 9 | B13: Journal | C13: França | D13: Privacy controls as an information source to reduce data poisoning in artificial intelligence-powered personalization | E13: https://doi.org/10.1016/j.jbusres.2022.07.045 | F13: 2022 | G13: Julien Cloarec | H13: França | I13: Science Direct | J13: RQ2 | K13: O texto não apresenta técnicas de IA aplicadas à automação de compliance (como NLP, ML ou sistemas especialistas). A IA é citada apenas como tecnologia de personalização utilizada por empresas, sem detalhamento técnico nem relação com tarefas regulatórias. | L13: O documento não descreve técnicas de IA para automação de conformidade, concentrando-se em metodologia experimental e estatística (análise de mediação para medidas repetidas) para entender o comportamento humano frente a sistemas de IA. O foco técnico é o impacto dos controles de privacidade (como configurações do Facebook) na percepção de autoeficácia e vulnerabilidade do usuário. | M13: O artigo não fornece informações específicas sobre quais técnicas de IA, como Processamento de Linguagem Natural, Aprendizado de Máquina ou Sistemas Especialistas, são mais empregadas na automação de tarefas de conformidade regulatória. O foco do estudo está na resposta comportamental dos consumidores (falsificação de dados) diante dos controles de privacidade em sistemas de personalização impulsionados por IA. | N13: Sim | O13: Sim | P13: =IF(OR(N13="",O13=""),"",IF(N13=O13,"Igual","Diferente")) -> Igual
A14: 9 | B14: Journal | C14: França | D14: Privacy controls as an information source to reduce data poisoning in artificial intelligence-powered personalization | E14: https://doi.org/10.1016/j.jbusres.2022.07.045 | F14: 2022 | G14: Julien Cloarec | H14: França | I14: Science Direct | J14: RQ3 | K14: O artigo não trata de compliance; contudo, menciona benefícios e desafios de IA no marketing digital: a personalização aumenta utilidade, mas gera vulnerabilidade, risco de vigilância e falsificação de dados pelos usuários. Também discute o paradoxo do controle e a assimetria de informação, que elevam sentimentos de risco e comportamentos defensivos. | L14: O desafio central citado é o "envenenamento de dados" (falsificação de informações pelos usuários), que ameaça a precisão dos modelos de IA e a economia digital. O benefício abordado refere-se à implementação de controles de privacidade que, ao aumentarem a autoeficácia do usuário e reduzirem a vulnerabilidade percebida, diminuem a falsificação, preservando a utilidade dos dados. | M14: Os benefícios e desafios específicos da IA em processos de conformidade, como redução de custos, viés algorítmico ou interpretabilidade, não são falados. Entretanto, o artigo aponta que a intervenção de marketing que fornece controles de privacidade pode reduzir a vulnerabilidade do consumidor e aumentar a autoeficácia, o que, por sua vez, reduz a falsificação de informações (melhorando a qualidade dos dados). O desafio de manter a utilidade dos dados versus a redução da vulnerabilidade do consumidor é um trade-off importante na gestão. | N14: Sim | O14: Sim | P14: =IF(OR(N14="",O14=""),"",IF(N14=O14,"Igual","Diferente")) -> Igual
A15: 9 | B15: Journal | C15: França | D15: Privacy controls as an information source to reduce data poisoning in artificial intelligence-powered personalization | E15: https://doi.org/10.1016/j.jbusres.2022.07.045 | F15: 2022 | G15: Julien Cloarec | H15: França | I15: Science Direct | J15: RQ4 | K15: O artigo não trata de LGPD, GDPR ou governança algorítmica. A discussão ética é centrada em privacidade do consumidor, responsabilidade digital corporativa e necessidade de empoderamento por meio de controles de privacidade, destacando como políticas e práticas claras podem reduzir vulnerabilidade e falsificação de dados. | L15: A ética é abordada através do conceito de responsabilidade digital corporativa, onde empresas devem capacitar consumidores sobre seus dados para evitar subversão e desequilíbrio de poder. O estudo alerta para o risco ético de controles de privacidade ilusórios e destaca que regulamentações de privacidade visam reduzir a vulnerabilidade do consumidor, exigindo transparência nas práticas de coleta de dados. | M15: O estudo aborda a ética e a governança através da noção de responsabilidade digital corporativa (CDR) e da importância da ética de privacidade iniciada pela empresa. As empresas devem incentivar os consumidores a estarem mais conscientes e a exercerem controle sobre a coleta e gestão de seus dados. A transparência e a confiança são princípios de design para dados de clientes, e as regulamentações de privacidade visam reduzir a vulnerabilidade do consumidor. A pesquisa sugere comparar políticas como o opt-in da União Europeia (UE) com o opt-out dos EUA. | N15: Sim | O15: Sim | P15: =IF(OR(N15="",O15=""),"",IF(N15=O15,"Igual","Diferente")) -> Igual
A16: 11 | B16: Journal | C16: Bélgica | D16: Exploring Automated GDPR-Compliance in Requirements Engineering: A Systematic Mapping Study | E16: https://ieeexplore.ieee.org/document/9420457/authors | F16: 2021 | G16: Abdel-Jaouad Aberkane; Geert Poels; Seppe Vanden Broucke | H16: Bélgica | I16: IEEE | J16: RQ1 | K16: O artigo não descreve automação direta de compliance; ele discute como IA no setor público exige práticas robustas de governança, gestão de riscos, documentação e supervisão humana para garantir conformidade com princípios como transparência, accountability e confiança institucional. | L16: O estudo foca na automação da conformidade com o GDPR durante a Engenharia de Requisitos (RE) usando Processamento de Linguagem Natural (NLP). A IA é aplicada para identificar e anonimizar dados pessoais em documentos, garantindo a privacidade desde o projeto (data protection by design). A governança emerge através da modelagem de obrigações legais em requisitos técnicos verificáveis. | M16: A Inteligência Artificial, especificamente o Processamento de Linguagem Natural (PLN), é utilizada para automatizar tarefas manuais na Engenharia de Requisitos (RE), auxiliando na conformidade com o GDPR. O principal benefício é unir os esforços financeiros e humanos substanciais exigidos pela conformidade regulatória, permitindo que as organizações adotem uma postura proativa. A governança é focada nos princípios de proteção de dados "by design" e "by default" | N16: Sim | O16: Sim | P16: =IF(OR(N16="",O16=""),"",IF(N16=O16,"Igual","Diferente")) -> Igual
A17: 11 | B17: Journal | C17: Bélgica | D17: Exploring Automated GDPR-Compliance in Requirements Engineering: A Systematic Mapping Study | E17: https://ieeexplore.ieee.org/document/9420457/authors | F17: 2021 | G17: Abdel-Jaouad Aberkane; Geert Poels; Seppe Vanden Broucke | H17: Bélgica | I17: IEEE | J17: RQ2 | K17: O texto não aponta técnicas específicas voltadas a compliance. Ele menciona sistemas de IA baseados em aprendizado de máquina empregados em decisões públicas, mas foca nos riscos e na necessidade de validação, auditoria e monitoramento contínuo, e não em técnicas como NLP ou sistemas especialistas. | L17: O trabalho identifica diversas técnicas de NLP aplicadas à Engenharia de Requisitos e GDPR, incluindo classificação de texto, extração de informação, Part-of-Speech (POS) tagging, reconhecimento de entidades nomeadas (NER) e pré-processamento (tokenização, stemming). Algoritmos de aprendizado de máquina, como redes neurais convolucionais, também são citados para classificação de texto. | M17: O PLN é a técnica de IA mais explorada na automação, com o objetivo de alcançar a conformidade automatizada com o GDPR na RE. Nos estudos que combinam NLP e GDPR, as abordagens mais frequentes são a classificação de texto e o pré-processamento. O aprendizado de máquina baseado em PLN também é identificado para a classificação e anonimização de dados pessoais em documentos, visando a conformidade. | N17: Parcialmente | O17: Sim | P17: =IF(OR(N17="",O17=""),"",IF(N17=O17,"Igual","Diferente")) -> Diferente | Q17: ChatGPT afirmou que o artigo "não descreve automação direta", enquanto Gemini e Humano detalharam o uso de NLP para conformidade.
A18: 11 | B18: Journal | C18: Bélgica | D18: Exploring Automated GDPR-Compliance in Requirements Engineering: A Systematic Mapping Study | E18: https://ieeexplore.ieee.org/document/9420457/authors | F18: 2021 | G18: Abdel-Jaouad Aberkane; Geert Poels; Seppe Vanden Broucke | H18: Bélgica | I18: IEEE | J18: RQ3 | K18: Entre os benefícios citados estão maior eficiência, escalabilidade e potencial melhoria na prestação de serviços públicos. Os desafios incluem opacidade algorítmica, riscos de vieses, falta de documentação, incapacidade de auditoria e impacto negativo na confiança pública caso o uso de IA não seja cuidadosamente controlado. | L18: Os benefícios incluem a redução do esforço manual e repetitivo na análise de documentos legais e requisitos, aumento da eficiência e garantia de conformidade proativa (by design). O estudo aponta a escassez de pesquisas na interseção específica de GDPR, NLP e RE como um desafio, indicando uma lacuna na automação completa da conformidade regulatória. | M18: Um benefício importante é a redução dos esforços e recursos humanos necessários para a conformidade com o GDPR, permitindo uma consciência e postura mais proativa das organizações. Os desafios citados refletem os conceitos do GDPR que exigem foco, sendo os mais prevalentes a Privacidade (30%), a Integridade e Confidencialidade (25%) e a Legalidade, Imparcialidade e Transparência (20%). | N18: Parcialmente | O18: Sim | P18: =IF(OR(N18="",O18=""),"",IF(N18=O18,"Igual","Diferente")) -> Diferente | Q18: ChatGPT foi vago sobre as técnicas. Gemini listou corretamente NLP, classificação e pré-processamento como a validação.
A19: 11 | B19: Journal | C19: Bélgica | D19: Exploring Automated GDPR-Compliance in Requirements Engineering: A Systematic Mapping Study | E19: https://ieeexplore.ieee.org/document/9420457/authors | F19: 2021 | G19: Abdel-Jaouad Aberkane; Geert Poels; Seppe Vanden Broucke | H19: Bélgica | I19: IEEE | J19: RQ4 | K19: O artigo enfatiza governança baseada em accountability, documentação, avaliação de riscos e mitigação de vieses, reforçando a necessidade de práticas robustas para garantir uso ético da IA. Embora não mencione diretamente LGPD/GDPR, aborda princípios equivalentes de transparência, controle, explicabilidade, supervisão humana e confiança pública. | L19: A governança é abordada através da tradução dos princípios do GDPR (como legalidade, justiça, transparência e responsabilidade) em requisitos de software. O estudo destaca a importância de técnicas de NLP para verificar a conformidade de políticas de privacidade e requisitos do sistema, assegurando que os direitos dos titulares dos dados sejam respeitados desde a concepção do software. | M19: O estudo aborda a governança e a ética focando na adesão ao GDPR, exigindo que as empresas implementem medidas técnicas e organizacionais apropriadas para impor os princípios de proteção de dados. Princípios éticos/regulatórios essenciais incluem a Prestação de Contas (Accountability) e a Legalidade, Imparcialidade e Transparência. A LGPD não é mencionada no estudo. | N19: Sim | O19: Sim | P19: =IF(OR(N19="",O19=""),"",IF(N19=O19,"Igual","Diferente")) -> Igual
A20: 12 | B20: Journal | C20: Luxemburgo | D20: NLP-Based Automated Compliance Checking of Data Processing Agreements Against GDPR | E20: https://ieeexplore.ieee.org/document/10167495 | F20: 2023 | G20: Orlando Amaral Cejas; Muhammad Ilyas Azeem; Sallam Abualhaija; Lionel C. Briand | H20: Luxemburgo | I20: IEEE | J20: RQ1 | K20: A IA é aplicada para automatizar verificações de aderência normativa, análise de documentos e detecção de riscos, especialmente usando modelos de PLN e aprendizado de máquina para interpretar regras e monitorar processos. Os benefícios incluem padronização, precisão e suporte à decisão, enquanto os desafios envolvem viés, explicabilidade e privacidade, além da necessidade de estruturas de governança para auditoria e supervisão humana. | L20: O estudo propõe uma abordagem automatizada (DERECHA) usando Processamento de Linguagem Natural (NLP) para verificar a conformidade de Acordos de Processamento de Dados (DPAs) contra o GDPR, traduzindo textos legais em requisitos de software. A estrutura de governança foca na validação de obrigações entre controladores e processadores de dados, garantindo que os contratos cubram requisitos mandatórios de proteção de dados antes da implementação do sistema. | M20: O Processamento de Linguagem Natural (PLN) é usado para verificar automaticamente a conformidade de Acordos de Processamento de Dados (DPAs) com o GDPR, decompondo os textos para identificar violações e informações faltantes. O principal benefício é a drástica redução do tempo e esforço manual (economia de 30 minutos para 2,5 minutos por DPA). O desafio reside na complexidade da linguagem legal e na necessidade de precisão, enquanto a governança emerge ao garantir que os DPAs sejam um pré-requisito completo para requisitos de sistemas de software compatíveis com privacidade. | N20: Sim | O20: Sim | P20: =IF(OR(N20="",O20=""),"",IF(N20=O20,"Igual","Diferente")) -> Igual
A21: 12 | B21: Journal | C21: Luxemburgo | D21: NLP-Based Automated Compliance Checking of Data Processing Agreements Against GDPR | E21: https://ieeexplore.ieee.org/document/10167495 | F21: 2023 | G21: Orlando Amaral Cejas; Muhammad Ilyas Azeem; Sallam Abualhaija; Lionel C. Briand | H21: Luxemburgo | I21: IEEE | J21: RQ2 | K21: As principais técnicas mencionadas incluem modelos de Processamento de Linguagem Natural para interpretação de requisitos regulatórios, aprendizado supervisionado e não supervisionado para classificação e detecção de anomalias, além de sistemas especialistas para regras decisórias em contextos normativos. | L21: A pesquisa emprega um pipeline de NLP que inclui tokenização, POS tagging, análise de dependência e análise semântica com recursos léxicos (WordNet e VerbNet), optando por não usar Machine Learning ou Deep Learning devido à escassez de dados rotulados. A técnica central é o uso de Quadros Semânticos (Semantic Frames) para decompor e comparar semanticamente as cláusulas dos contratos com os requisitos do GDPR. | M21: A técnica mais empregada é o Processamento de Linguagem Natural (PLN). O método se baseia em uma pipeline de PLN (tokenização, dependency parsing, semantic parsing) e regras, em vez de modelos robustos de Machine Learning (ML) ou Deep Learning (DL), devido à escassez de dados rotulados. | N21: Sim | O21: Sim | P21: =IF(OR(N21="",O21=""),"",IF(N21=O21,"Igual","Diferente")) -> Igual
A22: 12 | B22: Journal | C22: Luxemburgo | D22: NLP-Based Automated Compliance Checking of Data Processing Agreements Against GDPR | E22: https://ieeexplore.ieee.org/document/10167495 | F22: 2023 | G22: Orlando Amaral Cejas; Muhammad Ilyas Azeem; Sallam Abualhaija; Lionel C. Briand | H22: Luxemburgo | I22: IEEE | J22: RQ3 | K22: Os benefícios destacados são maior precisão na análise, redução de custos operacionais e agilidade na execução de tarefas repetitivas. Os desafios incluem riscos de viés algorítmico, falta de transparência dos modelos, dificuldades de interpretabilidade e possíveis conflitos com requisitos de privacidade dos dados. | L22: Os benefícios incluem alta eficiência (análise em 2,5 minutos versus 30 minutos manualmente) e precisão superior (89,1%) em comparação a ferramentas de NLP genéricas, reduzindo o esforço humano na revisão de textos legais complexos. Os desafios envolvem a ambiguidade inerente à linguagem jurídica, a dificuldade de interpretar contextos em listas enumeradas e a falta de conjuntos de dados suficientes para treinar modelos de aprendizado de máquina robustos. | M22: O principal benefício é a agilidade e eficiência, com a ferramenta DERECHA verificando DPAs em cerca de 2,5 minutos e alcançando 84,6% de acurácia. Os desafios incluem interpretação inconsistente de referências, perda de contexto em listas itemizadas, e o texto ruidoso/verboso nos documentos, que impactam a análise. | N22: Sim | O22: Sim | P22: =IF(OR(N22="",O22=""),"",IF(N22=O22,"Igual","Diferente")) -> Igual
A23: 12 | B23: Journal | C23: Luxemburgo | D23: NLP-Based Automated Compliance Checking of Data Processing Agreements Against GDPR | E23: https://ieeexplore.ieee.org/document/10167495 | F23: 2023 | G23: Orlando Amaral Cejas; Muhammad Ilyas Azeem; Sallam Abualhaija; Lionel C. Briand | H23: Luxemburgo | I23: IEEE | J23: RQ4 | K23: Os estudos enfatizam a necessidade de governança estruturada, com auditorias constantes, transparência nos algoritmos, supervisão humana e aderência a regulações como LGPD e GDPR. Ressalta-se também o papel da gestão em conformidade para garantir rastreabilidade, prestação de contas e uso ético da IA em processos regulatórios. | L23: A governança é tratada através da extração rigorosa de 45 requisitos de conformidade ("shall requirements") do GDPR em colaboração com especialistas jurídicos, criando uma ponte entre a lei e a engenharia de requisitos. O estudo assegura a adesão ao regulamento focando na verificação de DPAs, que são instrumentos legais cruciais para definir responsabilidades de privacidade e segurança entre as partes que processam dados pessoais. | M23: O estudo aborda a governança e a ética focando integralmente na adesão ao GDPR. O cerne da governança é garantir que o sistema cumpra os requisitos legalmente vinculativos listados nos DPAs. A conformidade visa impor Accountability e as obrigações específicas impostas aos controladores e processadores, como a implementação de medidas técnicas e organizacionais adequadas para a segurança de dados. A LGPD não é mencionada. | N23: Sim | O23: Sim | P23: =IF(OR(N23="",O23=""),"",IF(N23=O23,"Igual","Diferente")) -> Igual
A24: 13 | B24: Conference | C24: Luxemburgo | D24: LLM-assisted Extraction of Regulatory Requirements: A Case Study on the GDPR | E24: https://ieeexplore.ieee.org/document/11190380 | F24: 2025 | G24: Sallam Abualhaija; Marcello Ceci; Nicolas Sannier; Domenico Bianculli; Salomé Lannier; Martina Siclari | H24: Luxemburgo | I24: IEEE | J24: RQ1 | K24: A IA é aplicada por meio de LLMs, NLP e RAG para extrair automaticamente requisitos regulatórios (como direitos do GDPR), reduzindo a lacuna entre interpretação legal e desenvolvimento de software. Os benefícios incluem automação e apoio a engenheiros; desafios incluem perspectiva incorreta, requisitos genéricos e limitações na interpretação jurídica; e a governança envolve uso responsável, referência a fontes normativas e colaboração com especialistas. | L24: O estudo propõe a abordagem XTRAREG, que utiliza Grandes Modelos de Linguagem (LLMs) e Retrieval Augmented Generation (RAG) para automatizar a extração de requisitos de privacidade do GDPR, preenchendo a lacuna entre a lei e o desenvolvimento de software. A governança emerge através da engenharia de prompt (Chain-of-Thought) que exige que o LLM explique o raciocínio por trás de cada requisito gerado, auxiliando analistas humanos na validação de conformidade | M24: A IA, via LLMs e PLN, é aplicada para automatizar a extração de requisitos detalhados de privacidade a partir de documentos legais (GDPR e fontes complementares). Os benefícios são a alta acurácia (81.8% ACC, 85.7% PRT) na geração desses requisitos e o auxílio a engenheiros com lacunas de conhecimento legal. Os desafios incluem baixa cobertura, geração de requisitos genéricos e a adoção de perspectivas incorretas pelo LLM, enquanto a governança foca na capacidade de justificar a conformidade usando fontes corretas. | N24: Sim | O24: Sim | P24: =IF(OR(N24="",O24=""),"",IF(N24=O24,"Igual","Diferente")) -> Igual
A25: 13 | B25: Conference | C25: Luxemburgo | D25: LLM-assisted Extraction of Regulatory Requirements: A Case Study on the GDPR | E25: https://ieeexplore.ieee.org/document/11190380 | F25: 2025 | G25: Sallam Abualhaija; Marcello Ceci; Nicolas Sannier; Domenico Bianculli; Salomé Lannier; Martina Siclari | H25: Luxemburgo | I25: IEEE | J25: RQ2 | K25: As técnicas mais empregadas são NLP, grandes modelos de linguagem (LLMs), Zero-shot learning, Chain-of-Thought e Retrieval-Augmented Generation, usadas para interpretar textos legais, gerar requisitos detalhados e cruzar fontes normativas como GDPR e diretrizes do EDPB. | L25: A pesquisa emprega Grandes Modelos de Linguagem (LLMs), especificamente GPT-3.5 e GPT-4o, combinados com a técnica de Geração Aumentada por Recuperação (RAG) para incorporar conhecimento jurídico específico nos prompts. Além disso, utiliza técnicas de engenharia de prompt como Zero-Shot Learning (ZSL) para instruções diretas e Chain-of-Thought (CoT) para articular o raciocínio da extração de requisitos. | M25: As técnicas mais empregadas são LLMs em conjunto com o PLN. O método citado no artigo, XTRAREG, utiliza especificamente a Geração Aumentada por Recuperação (RAG) para incorporar conhecimento legal específico nos prompts, e técnicas como Zero-Shot Learning e Chain-of-Thought são usadas para instruir o LLM a extrair os requisitos. | N25: Sim | O25: Sim | P25: =IF(OR(N25="",O25=""),"",IF(N25=O25,"Igual","Diferente")) -> Igual
A26: 13 | B26: Conference | C26: Luxemburgo | D26: LLM-assisted Extraction of Regulatory Requirements: A Case Study on the GDPR | E26: https://ieeexplore.ieee.org/document/11190380 | F26: 2025 | G26: Sallam Abualhaija; Marcello Ceci; Nicolas Sannier; Domenico Bianculli; Salomé Lannier; Martina Siclari | H26: Luxemburgo | I26: IEEE | J26: RQ3 | K26: Os benefícios incluem geração automática de requisitos, aumento de precisão e apoio ao processo de compliance; já os desafios envolvem viés, referências incompletas, interpretações erradas, pouca cobertura e risco de requisitos não acionáveis. Há ainda dificuldades em capturar exceções legais e garantir alinhamento normativo. | L26: Os benefícios incluem a automação da extração de requisitos com alta precisão (até 85,7% para o direito à portabilidade), auxiliando engenheiros na implementação técnica de direitos legais complexos. Os desafios envolvem a tendência dos LLMs de gerar requisitos genéricos ou alucinar, e a dificuldade em referenciar fontes legais adicionais além do GDPR, mesmo quando explicitamente instruídos via RAG. | M26: O principal benefício é a agilidade e precisão na geração de requisitos técnicos detalhados, com acurácia de 81% a 85.7% para os direitos de acesso e portabilidade no GDPR, e a redução do risco de desenvolvimento de software não compatível. Os desafios incluem a baixa cobertura e a dificuldade em fornecer referências legais completas ou corretas. | N26: Sim | O26: Sim | P26: =IF(OR(N26="",O26=""),"",IF(N26=O26,"Igual","Diferente")) -> Igual
A27: 13 | B27: Conference | C27: Luxemburgo | D27: LLM-assisted Extraction of Regulatory Requirements: A Case Study on the GDPR | E27: https://ieeexplore.ieee.org/document/11190380 | F27: 2025 | G27: Sallam Abualhaija; Marcello Ceci; Nicolas Sannier; Domenico Bianculli; Salomé Lannier; Martina Siclari | H27: Luxemburgo | I27: IEEE | J27: RQ4 | K27: Os estudos tratam governança e ética ao destacar a necessidade de fundamentação normativa correta, transparência nas referências legais, prevenção de uso inadequado das capacidades dos LLMs e apoio contínuo de especialistas para garantir aderência ao GDPR e a diretrizes oficiais. Limitações éticas incluem interpretações errôneas e risco de incompletude jurídica. | L27: O estudo aborda a governança focando na extração correta de requisitos para garantir o desenvolvimento de software lícito e ético sob o GDPR, especificamente para os direitos de acesso e portabilidade dos titulares de dados. A ética no uso da IA é tratada posicionando os LLMs como assistentes de especialistas humanos para mitigar riscos de alucinação e garantir a validade jurídica das saídas geradas | M27: Os estudos abordam a governança e a ética focando na adesão ao GDPR e na necessidade de Accountability. A transparência é considerada um princípio de design importante, sendo explorada a técnica Chain-of-Thought para fazer com que o LLM articule o raciocínio por trás da extração dos requisitos. O foco é garantir que o software seja legal e ético, incorporando requisitos detalhados obtidos de fontes autoritativas além da legislação primária, embora a LGPD não seja mencionada. | N27: Sim | O27: Sim | P27: =IF(OR(N27="",O27=""),"",IF(N27=O27,"Igual","Diferente")) -> Igual
A28: 14 | B28: Conference | C28: Indonésia | D28: Understanding the Basics of Privacy Engineering: An Ontological Approach | E28: https://ieeexplore.ieee.org/document/10929291 | F28: 2025 | G28: Agus Hariyanto; Sawung Murdha Anggara; Ana Heryana; Suhardi | H28: Indonésia | I28: IEEE | J28: RQ1 | K28: Segundo o documento, a integração de IA ocorre principalmente por meio de metodologias de privacy engineering e automação orientada por princípios como privacy-by-design, alinhando práticas ao GDPR e outras normas. Isso fortalece a detecção precoce de riscos e a aplicação de salvaguardas, mas exige práticas organizacionais maduras, colaboração com especialistas e cultura de conformidade. | L28: O estudo destaca o papel de tecnologias emergentes, como inteligência artificial e blockchain, para fortalecer as salvaguardas de privacidade e manter a conformidade regulatória, propondo a integração de considerações de privacidade em metodologias de desenvolvimento como Agile. A estrutura de governança foca na responsabilidade (accountability), confiança do usuário e manuseio ético de dados, utilizando uma Ontologia de Engenharia de Privacidade para estruturar práticas e comunicação entre as partes interessadas. | M28: A IA é tratada no contexto de práticas de privacy engineering, atuando como suporte à automação de processos que reforçam a aderência a normas como o GDPR. Ela contribui para fortalecer salvaguardas, antecipar riscos e apoiar decisões, mas depende de governança madura, participação de especialistas e alinhamento contínuo às exigências regulatórias. | N28: Sim | O28: Sim | P28: =IF(OR(N28="",O28=""),"",IF(N28=O28,"Igual","Diferente")) -> Igual
A29: 14 | B29: Conference | C29: Indonésia | D29: Understanding the Basics of Privacy Engineering: An Ontological Approach | E29: https://ieeexplore.ieee.org/document/10929291 | F29: 2025 | G29: Agus Hariyanto; Sawung Murdha Anggara; Ana Heryana; Suhardi | H29: Indonésia | I29: IEEE | J29: RQ2 | K29: O texto menciona o uso de técnicas ligadas à engenharia de privacidade e práticas automatizadas que suportam avaliação contínua de riscos e conformidade, o que inclui métodos de análise orientada a dados e automação de verificações. Aparecem também referências gerais ao uso de métodos de privacy engineering e práticas de detecção de violações. (O arquivo não descreve técnicas específicas como NLP ou ML, portanto a resposta se limita ao que realmente aparece.) | L29: O texto enfatiza técnicas de preservação de privacidade utilizadas em Ciência de Dados e IA, especificamente aprendizado federado (federated learning), privacidade diferencial e criptografia homomórfica, que permitem análises colaborativas sem expor dados sensíveis. Além disso, menciona-se o uso de algoritmos de aprendizado de máquina, alertando, contudo, para sua capacidade de desanonimizar dados através da correlação de pontos de dados díspares. | M29: O artigo não descreve técnicas específicas como NLP, ML ou sistemas especialistas; ele foca em práticas de engenharia de privacidade e metodologias automatizadas de avaliação de riscos e conformidade. A automação mencionada está ligada mais à aplicação sistemática de princípios regulatórios do que ao uso explícito de técnicas avançadas de IA. | N29: Sim | O29: Sim | P29: =IF(OR(N29="",O29=""),"",IF(N29=O29,"Igual","Diferente")) -> Igual
A30: 14 | B30: Conference | C30: Indonésia | D30: Understanding the Basics of Privacy Engineering: An Ontological Approach | E30: https://ieeexplore.ieee.org/document/10929291 | F30: 2025 | G30: Agus Hariyanto; Sawung Murdha Anggara; Ana Heryana; Suhardi | H30: Indonésia | I30: IEEE | J30: RQ3 | K30: Os benefícios apontados incluem detecção antecipada de riscos, melhoria de salvaguardas, criação de métricas padronizadas de privacidade e adaptação contínua a ameaças e exigências regulatórias. Entre os desafios estão a necessidade de capacitação, maturidade organizacional, adaptação a um cenário regulatório dinâmico e riscos associados à gestão inadequada de dados sensíveis. | L30: Os benefícios incluem a capacidade de realizar análises significativas em grandes volumes de dados protegendo informações pessoais, enquanto os desafios envolvem a dificuldade das leis atuais (como GDPR e CCPA) em abordar questões específicas da IA, como a transparência na tomada de decisões automatizada. Um desafio crítico citado é a vulnerabilidade da exposição de PII devido a técnicas sofisticadas de agregação de dados e a inferência de detalhes sensíveis por modelos de IA. | M30: Os benefícios destacados incluem maior capacidade de detectar problemas de privacidade, adoção de medidas preventivas e criação de métricas padronizadas para monitoramento contínuo. Entre os desafios, o texto enfatiza limitações organizacionais, necessidade de adaptação constante e riscos associados ao uso inadequado ou insuficiente de práticas de proteção de dados. | N30: Sim | O30: Sim | P30: =IF(OR(N30="",O30=""),"",IF(N30=O30,"Igual","Diferente")) -> Igual
... A63: 33 | B63: Journal | C63: Afeganistão | D63: Securing social network user data in large language model deployments: challenges and best practices | E63: https://www.scopus.com/pages/publications/105016088492?origin=resultslist | F63: 2025 | G63: Jalali, Nasir Ahmad, Hongsong, Chen | H63: Afeganistão | I63: Scopus | J63: RQ4 | K63: O estudo enfatiza práticas de governança como controle de acesso, anonimização, comitês éticos, federated learning e técnicas de segurança que buscam garantir transparência, responsabilidade e proteção de dados, alinhando-se a princípios exigidos por legislações como GDPR/LGPD, embora não as cite diretamente. | L63: O artigo aborda a governança citando explicitamente as multas do GDPR aplicadas à Meta como exemplo da necessidade de conformidade legal e propõe o uso de Blockchain para garantir registros imutáveis e transparência. A ética é tratada através da recomendação de comitês de controle de privacidade e políticas de anonimização para assegurar a prestação de contas e proteção de dados pessoais. | M63: Os estudos abordam a governança focando na construção de uma IA confiável e na necessidade de alinhar a inovação com padrões éticos e sociais. A prestação de contas e a transparência são suportadas por estruturas de controle de acesso e pelo uso de Blockchain para rastreamento. O estudo menciona explicitamente a adesão ao GDPR, mas a regulamentação brasileira LGPD não é mencionada. | N63: Sim | O63: Sim | P63: =IF(OR(N63="",O63=""),"",IF(N63=O63,"Igual","Diferente")) -> Igual
A64: 34 | B64: Conference | C64: Grécia | D64: Designing connected and automated vehicles around legal and ethical concerns: Data protection as a corporate social responsibility | E64: https://www.scopus.com/pages/publications/85104660519?origin=resultslist | F64: 2021 | G64: Balboni, Paolo;Francis, Kate;Botsi, Anastasia;Barata, Martim Taborda | H64: Países Baixo e Itália | J64: RQ1 | K64: O artigo mostra que sistemas baseados em IA em veículos conectados e autônomos desafiam diretamente a conformidade com GDPR, ePrivacy e NIS, exigindo controles sobre finalidades, minimização, segurança e transparência. A IA amplia riscos devido ao grande volume e à autonomia do processamento, exigindo estruturas de governança com avaliações de impacto, accountability, segurança por design e ética incorporada ao desenvolvimento. | L64: O texto não aborda o uso de IA para automatizar a conformidade, mas sim os desafios que a IA em veículos (CAVs) impõe à conformidade regulatória. A estrutura de governança proposta é a "Proteção de Dados como Responsabilidade Social Corporativa" (DPCSR), que integra ética e direitos humanos no ciclo de vida do desenvolvimento para mitigar riscos legais. | M64: A IA em veículos conectados e automatizados (CAVs) é usada para processamento autônomo de dados e realizar funções de condução, mas apresenta novos desafios de conformidade regulatória e legal em relação ao GDPR e ePrivacy. Os desafios incluem o conflito da necessidade de grandes datasets para o treinamento da IA com o princípio da minimização de dados, e tensões com o princípio da limitação de finalidade. A governança é abordada por uma estrutura holística chamada "Data Protection as a Corporate Social Responsibility" (DPCSR), que visa incorporar ética e transparência no design | N64: Sim | O64: Sim | P64: =IF(OR(N64="",O64=""),"",IF(N64=O64,"Igual","Diferente")) -> Igual
A65: 34 | B65: Conference | C65: Grécia | D65: Designing connected and automated vehicles around legal and ethical concerns: Data protection as a corporate social responsibility | E65: https://www.scopus.com/pages/publications/85104660519?origin=resultslist | F65: 2021 | G65: Balboni, Paolo;Francis, Kate;Botsi, Anastasia;Barata, Martim Taborda | H65: Países Baixo e Itália | I65: Scopus | J65: RQ2 | K65: O texto discute IA de forma ampla, enfatizando algoritmos e sistemas autônomos usados para interpretar dados de sensores, apoiar decisões e operar funções automatizadas. Embora não detalhe algoritmos específicos, menciona sistemas automatizados baseados em machine learning que dependem de grandes conjuntos de dados e processamento contínuo, exigindo governança rigorosa de dados e proteção por design. | L65: O documento não cita técnicas de IA utilizadas para automatizar tarefas de conformidade. Ele menciona o uso de "conjuntos de dados relativamente grandes para treinar e alavancar funcionalidades de IA" (Machine Learning) para a operação autônoma dos veículos, destacando o conflito dessa prática com o princípio da minimização de dados. | M65: O foco do estudo é a aplicação da IA em veículos CAVs, onde são utilizados sensores e IA para funções autônomas de condução. A IA requer o uso de grandes conjuntos de dados para treinar e alavancar suas funcionalidades, sendo o uso de dados sintéticos uma solução mencionada para o treinamento de modelos de CAVs, garantindo precisão e segurança. O texto não especifica quais técnicas de IA (como PLN ou Aprendizado de Máquina) são empregadas para a automação geral de tarefas de conformidade (RegTech) | N65: Sim | O65: Sim | P65: =IF(OR(N65="",O65=""),"",IF(N65=O65,"Igual","Diferente")) -> Igual
A66: 34 | B66: Conference | C66: Grécia | D66: Designing connected and automated vehicles around legal and ethical concerns: Data protection as a corporate social responsibility | E66: https://www.scopus.com/pages/publications/85104660519?origin=resultslist | F66: 2021 | G66: Balboni, Paolo;Francis, Kate;Botsi, Anastasia;Barata, Martim Taborda | H66: Países Baixo e Itália | I66: Scopus | J66: RQ3 | K66: Os benefícios incluem maior eficiência operacional, funcionalidades avançadas e potencial melhora em segurança e mobilidade. Os desafios centrais são conflitos com princípios de proteção de dados (minimização, limitação de finalidade, transparência), riscos de segurança devido ao grande ecossistema conectado, necessidade de grandes volumes de dados e risco de usos incompatíveis. Também há complexidade no cumprimento de obrigações legais e no gerenciamento de múltiplos atores envolvidos. | L66: O texto foca nos desafios de conformidade da IA, citando conflitos com a limitação de finalidade devido ao processamento autônomo , dificuldades com a minimização de dados e a falta de transparência devido à complexidade dos algoritmos ("caixa preta"). Benefícios citados referem-se à segurança viária e impacto ambiental dos CAVs, não à automação da conformidade. | M66: Os benefícios associados à IA em CAVs incluem o potencial de aumentar a segurança rodoviária, reduzir o impacto ambiental, melhorar a mobilidade e maximizar os benefícios para os usuários. Os desafios principais são a complexidade dos sistemas de IA, que compromete a transparência e a interpretabilidade das decisões automatizadas, e a criação de conflitos regulatórios, como oposição aos princípios de minimização de dados e limitação de finalidade. Preocupações éticas como viés e discriminação são abordadas pelo requisito de ter atividades de processamento de dados confiáveis que ativamente se oponham a eles | N66: Sim | O66: Sim | P66: =IF(OR(N66="",O66=""),"",IF(N66=O66,"Igual","Diferente")) -> Igual
A67: 34 | B67: Conference | C67: Grécia | D67: Designing connected and automated vehicles around legal and ethical concerns: Data protection as a corporate social responsibility | E67: https://www.scopus.com/pages/publications/85104660519?origin=resultslist | F67: 2021 | G67: Balboni, Paolo;Francis, Kate;Botsi, Anastasia;Barata, Martim Taborda | H67: Países Baixo e Itália | I67: Scopus | J67: RQ4 | K67: Os estudos reforçam que governança ética exige transparência, justificabilidade das decisões algorítmicas, supervisão humana, fairness by design, data protection by design and by default e avaliações de impacto (DPIA). A conformidade com GDPR é tratada como requisito mínimo, devendo ser complementada por práticas éticas que assegurem responsabilidade, mitigação de riscos, segurança robusta e respeito aos direitos fundamentais no uso de IA em sistemas complexos como CAVs. | L67: O estudo foca no GDPR e propõe a integração de "Fairness by Design", transparência e supervisão humana no design dos veículos. A governança exige que os controladores demonstrem responsabilidade (accountability) e forneçam informações explicáveis sobre a lógica algorítmica para garantir um processamento justo e confiável. | M67: A governança e a ética são cruciais no uso da IA, sendo promovida uma abordagem holística, Data Protection as a Corporate Social Responsibility (DPCSR), que integra ética, justiça (fairness), transparência e segurança no design, indo além dos requisitos mínimos do GDPR. A prestação de contas (accountability) é um princípio fundamental do GDPR, exigindo que os atores (fabricantes, desenvolvedores) demonstrem que os dados são processados de forma transparente, sendo um desafio a alocação clara dos papéis de controlador e processador. A transparência é essencial para que o sujeito dos dados entenda o processamento e a lógica envolvida nas decisões automatizadas da IA, sendo sugerido o uso de ícones padronizados para comunicar a coleta de dados. A regulamentação brasileira LGPD não é mencionada; o foco é o GDPR, ePrivacy e NISD. | N67: Sim | O67: Sim | P67: =IF(OR(N67="",O67=""),"",IF(N67=O67,"Igual","Diferente")) -> Igual
A68: 35 | B68: Journal | C68: Gana | D68: The Role of AI in Shaping the Discharge of Duties of University Administrators: A Systematic Review | E68: https://www.scopus.com/pages/publications/105015343709?origin=resultslist | F68: 2025 | G68: Buame, Juliana Abilla, Tiika, Bernard John, Lotsu, Setor Aku | H68: Gana | I68: Scopus | J68: RQ1 | K68: O artigo mostra que IA é aplicada para apoiar decisões administrativas, automatizar tarefas, analisar grandes volumes de dados e monitorar processos institucionais, aumentando eficiência e precisão. Os principais desafios envolvem privacidade, vieses algorítmicos, transparência e ausência de estruturas éticas e legais claras, exigindo governança adequada. | L68: A IA é aplicada para monitorar a conformidade institucional (como frequência e reuniões) e automatizar tarefas administrativas, exigindo estruturas de governança alinhadas a leis de proteção de dados. Os benefícios incluem maior eficiência e produtividade, enquanto os desafios envolvem déficits de infraestrutura, falta de expertise técnica e riscos de vigilância injustificada ou uso indevido de dados. | M68: A IA (ML, NLP, predictive analytics) é aplicada em sistemas de informação universitários para aprimorar a tomada de decisão e automatizar tarefas de gestão como monitoramento de desempenho estudantil. Os benefícios são o aumento da eficiência, produtividade e a personalização do aprendizado. Os desafios incluem infraestrutura deficitária, falta de expertise e a ausência de frameworks éticos/legais específicos. | N68: Sim | O68: Sim | P68: =IF(OR(N68="",O68=""),"",IF(N68=O68,"Igual","Diferente")) -> Igual
A69: 35 | B69: Journal | C69: Gana | D69: The Role of AI in Shaping the Discharge of Duties of University Administrators: A Systematic Review | E69: https://www.scopus.com/pages/publications/105015343709?origin=resultslist | F69: 2025 | G69: Buame, Juliana Abilla, Tiika, Bernard John, Lotsu, Setor Aku | H69: Gana | I69: Scopus | J69: RQ2 | K69: As técnicas mais citadas incluem machine learning, processamento de linguagem natural (NLP), chatbots, assistentes virtuais, sistemas de recomendação, analytics, e modelos preditivos utilizados para automação de análises, atendimento e gestão de dados. | L69: As técnicas predominantes incluem Machine Learning e Análise Preditiva para previsão de desempenho e detecção de riscos, além de chatbots baseados em Processamento de Linguagem Natural (PLN) para serviços de atendimento. Essas ferramentas são integradas a Sistemas de Informação Estudantil (SIS) para gerenciar dados, verificar registros e automatizar avaliações. | M69: As técnicas mais empregadas são o Machine Learning e Processamento de Linguagem Natural (NLP). Elas são usadas em Análise Preditiva para estimar taxas de abandono e desempenho, e em chatbots/assistentes virtuais para aprimorar a comunicação e satisfação do usuário. O uso de Sistemas de Informação Estudantil (SIS) também é fundamental para proteger e verificar registros de dados. | N69: Sim | O69: Sim | P69: =IF(OR(N69="",O69=""),"",IF(N69=O69,"Igual","Diferente")) -> Igual
A70: 35 | B70: Journal | C70: Gana | D70: The Role of AI in Shaping the Discharge of Duties of University Administrators: A Systematic Review | E70: https://www.scopus.com/pages/publications/105015343709?origin=resultslist | F70: 2025 | G70: Buame, Juliana Abilla, Tiika, Bernard John, Lotsu, Setor Aku | H70: Gana | I70: Scopus | J70: RQ3 | K70: Os benefícios relatados incluem aumento de eficiência administrativa, automação de processos, apoio à decisão, personalização e melhoria na gestão de informações. Já os desafios envolvem custos, falta de infraestrutura, limitações técnicas, vieses algorítmicos, riscos à privacidade, pouca transparência e resistência institucional. | L70: Os benefícios centrais são o aumento da eficiência, precisão em previsões orçamentárias e detecção de plágio, permitindo que administradores foquem em tarefas estratégicas. Os desafios críticos incluem o viés algorítmico (discriminação), a falta de interpretabilidade ("caixa preta"), violações de privacidade e ambiguidades legais sobre responsabilidade em decisões automatizadas. | M70: Os benefícios são a melhoria da eficiência institucional, a redução da carga de trabalho e o fornecimento de insights baseados em dados para decisões mais rápidas. Os desafios críticos são a privacidade e segurança de dados sensíveis, o viés em algoritmos que pode perpetuar injustiças, e a falta de transparência que transforma os sistemas em "caixas pretas". | N70: Sim | O70: Sim | P70: =IF(OR(N70="",O70=""),"",IF(N70=O70,"Igual","Diferente")) -> Igual
A71: 35 | B71: Journal | C71: Gana | D71: The Role of AI in Shaping the Discharge of Duties of University Administrators: A Systematic Review | E71: https://www.scopus.com/pages/publications/105015343709?origin=resultslist | F71: 2025 | G71: Buame, Juliana Abilla, Tiika, Bernard John, Lotsu, Setor Aku | H71: Gana | I71: Scopus | J71: RQ4 | K71: Os estudos destacam que a adoção de IA exige estruturas de governança que garantam transparência, justiça, responsabilidade e proteção de dados, alinhando-se a princípios presentes em normas como GDPR e leis nacionais de proteção de dados. O artigo alerta que a ausência de diretrizes éticas e legais pode gerar discriminação, violações de privacidade e riscos à accountability. | L71: Os estudos abordam a governança exigindo transparência (explicabilidade), justiça e responsabilidade para evitar discriminação algorítmica e manter a confiança pública nas instituições. A ética é tratada através da necessidade estrita de adesão a regulamentações de dados, citando explicitamente o GDPR e a Lei de Proteção de Dados de Gana (Act 843) como referenciais. | M71: A governança exige que os administradores garantam a transparência, a prestação de contas e o cumprimento dos princípios éticos de decência humana. A adesão regulatória explícita foca no GDPR (UE) e na Lei de Proteção de Dados de Gana, sendo que o estudo destaca o risco de violação de direitos sem frameworks legais específicos. A regulamentação brasileira LGPD não é mencionada nas fontes. | N71: Sim | O71: Sim | P71: =IF(OR(N71="",O71=""),"",IF(N71=O71,"Igual","Diferente")) -> Igual
A72: 37 | B72: Journal | C72: Suíça | D72: Impact of EU Laws on AI Adoption in Smart Grids: A Review of Regulatory Barriers, Technological Challenges, and Stakeholder Benefits | E72: https://www.scopus.com/pages/publications/105008942662?origin=resultslist | F72: 2025 | G72: Jørgensen, Bo Nørregaard, Gunasekaran, Saraswathy Shamini, Ma, Zheng Grace | H72: Dinamarca | I72: Scopus | J72: RQ1 | K72: A IA é aplicada em smart grids para atender exigências regulatórias como GDPR, AI Act e NIS2, ajudando no processamento seguro de dados, na detecção de anomalias e na automação de decisões sob requisitos de transparência e supervisão humana. Os benefícios incluem maior confiança dos consumidores, melhor segurança e operação mais eficiente. Os desafios envolvem forte carga regulatória, altos custos de conformidade, exigências de explicabilidade, proteção de dados e responsabilidade legal. Governança é estruturada por GDPR, AI Act, Data Act, DGA e diretivas de cibersegurança, que impõem regras de transparência, gestão de riscos, privacidade e accountability. | L72: A IA é aplicada para monitorar a implementação de políticas e metas de eficiência energética, apoiada por estruturas como o Data Governance Act que facilitam o compartilhamento seguro de dados. Os benefícios incluem maior estabilidade da rede e confiança do consumidor, enquanto os desafios envolvem altos custos de conformidade, barreiras regulatórias de privacidade e a necessidade de governança de dados robusta. | M72: A IA é aplicada em smart grids para análise preditiva, controle autônomo da rede e otimização de energias renováveis. Os benefícios incluem maior estabilidade da rede e redução de custos. Os desafios são a conformidade com o GDPR, cibersegurança (NIS2) e a necessidade de transparência algorítmica (AI Act). A governança é estruturada pelas leis da UE (GDPR, AI Act, NIS2) para garantir uma IA confiável. | N72: Sim | O72: Sim | P72: =IF(OR(N72="",O72=""),"",IF(N72=O72,"Igual","Diferente")) -> Igual
A73: 37 | B73: Journal | C73: Suíça | D73: Impact of EU Laws on AI Adoption in Smart Grids: A Review of Regulatory Barriers, Technological Challenges, and Stakeholder Benefits | E73: https://www.scopus.com/pages/publications/105008942662?origin=resultslist | F73: 2025 | G73: Jørgensen, Bo Nørregaard, Gunasekaran, Saraswathy Shamini, Ma, Zheng Grace | H73: Dinamarca | I73: Scopus | J73: RQ2 | K73: O artigo menciona o uso de machine learning, deep learning, detecção de anomalias, previsão de demanda, controle autônomo e técnicas de aprendizado distribuído como federated learning para respeitar a privacidade. Também discute IA explicável (XAI), modelos híbridos e sistemas automatizados de decisão aplicados ao gerenciamento de dados e segurança em redes elétricas. | L73: As técnicas mais empregadas incluem Machine Learning e Deep Learning para análises preditivas e detecção de anomalias em tempo real , além de Federated Learning para treinar modelos de forma descentralizada preservando a privacidade. O estudo também cita o uso de sistemas especialistas (baseados em regras) e IA explicável (XAI) para garantir a interpretabilidade das decisões operacionais | M73: As técnicas de IA mais empregadas são o Machine Learning para análise preditiva e controle autônomo da rede. Para conformidade (privacidade e segurança), são explorados o Aprendizado Federado e o Edge Computing para processar dados descentralizadamente. O GDPR e o AI Act exigem o uso de anonimização/pseudonimização e IA Explicável (XAI) para transparência. | N73: Sim | O73: Sim | P73: =IF(OR(N73="",O73=""),"",IF(N73=O73,"Igual","Diferente")) -> Igual
A74: 37 | B74: Journal | C74: Suíça | D74: Impact of EU Laws on AI Adoption in Smart Grids: A Review of Regulatory Barriers, Technological Challenges, and Stakeholder Benefits | E74: https://www.scopus.com/pages/publications/105008942662?origin=resultslist | F74: 2025 | G74: Jørgensen, Bo Nørregaard, Gunasekaran, Saraswathy Shamini, Ma, Zheng Grace | H74: Dinamarca | I74: Scopus | J74: RQ3 | K74: Os principais benefícios incluem maior eficiência do sistema, confiabilidade da rede, redução de custos operacionais, otimização de recursos e aumento da confiança dos usuários por meio de práticas transparentes e seguras. Os desafios envolvem privacidade, riscos de viés, dificuldades de interpretabilidade, elevados custos de conformidade, incerteza jurídica, integração de dados, interoperabilidade limitada e exigências rigorosas de cibersegurança. | L74: Os principais benefícios citados são a melhoria da estabilidade da rede, otimização de custos operacionais e alinhamento com metas de sustentabilidade. Já os desafios incluem requisitos rigorosos de proteção de dados (GDPR), a necessidade de transparência algorítmica (explicabilidade), riscos de cibersegurança e incertezas sobre responsabilidade civil em decisões autônomas. | M74: Os benefícios são a melhoria da estabilidade e resiliência da rede, otimização de custos e aumento da confiança do consumidor. Os desafios incluem o custo e a sobrecarga de conformidade (DPIAs e AI Act), cibersegurança (ataques adversários), e a necessidade de interpretabilidade (problema black-box) dos algoritmos. | N74: Sim | O74: Sim | P74: =IF(OR(N74="",O74=""),"",IF(N74=O74,"Igual","Diferente")) -> Igual
A75: 37 | B75: Journal | C75: Suíça | D75: Impact of EU Laws on AI Adoption in Smart Grids: A Review of Regulatory Barriers, Technological Challenges, and Stakeholder Benefits | E75: https://www.scopus.com/pages/publications/105008942662?origin=resultslist | F75: 2025 | G75: Jørgensen, Bo Nørregaard, Gunasekaran, Saraswathy Shamini, Ma, Zheng Grace | H75: Dinamarca | I75: Scopus | J75: RQ4 | K75: Os estudos abordados reforçam a necessidade de prestação de contas, transparência, explicabilidade, supervisão humana e proteção de dados alinhadas ao GDPR e ao AI Act. A governança enfatiza privacy by design, avaliações de impacto (DPIA), regras claras de responsabilidade, certificações de cibersegurança e práticas de uso ético para garantir confiança, segurança e conformidade com normas como GDPR, NIS2 e legislação europeia emergente. | L75: Os estudos abordam a governança através do EU AI Act, que exige supervisão humana, avaliação de riscos e transparência para sistemas de IA de alto risco em infraestruturas críticas. A ética e a conformidade com o GDPR são tratadas como fundamentais para uma "IA confiável", exigindo práticas de privacy-by-design e transparência algorítmica para garantir a prestação de contas e a confiança do consumidor. | M75: A ética e a governança são cruciais para garantir uma IA confiável e incluem mandatos de transparência, prestação de contas (accountability) e supervisão humana. O estudo foca intensamente na adesão ao GDPR (privacidade) e ao EU AI Act (risco e transparência), com o objetivo de construir a confiança do consumidor. A regulamentação brasileira LGPD não é mencionada nas fontes. | N75: Sim | O75: Sim | P75: =IF(OR(N75="",O75=""),"",IF(N75=O75,"Igual","Diferente")) -> Igual
A76: 40 | B76: Journal | C76: Suíça | D76: The Development and Construction of City Information Modeling (CIM): A Survey from Data Perspective | E76: https://www.scopus.com/pages/publications/105004887982?origin=resultslist | F76: 2025 | G76: Yu, Wenya, Zhou, Xiaowei, Wang, Dongsheng, Dong, Junyu | H76: China | I76: Scopus | J76: RQ1 | K76: A IA não é o foco direto do estudo, mas aparece integrada a sistemas que dependem de rastreabilidade, auditoria e governança de dados para garantir conformidade regulatória em ambientes multi-cloud. Os benefícios incluem transparência, imutabilidade e auditoria confiável via blockchain. Os desafios envolvem interoperabilidade, segurança e integridade de dados distribuídos. | L76: A IA é integrada ao CIM para otimizar a gestão urbana e ambiental via análise preditiva e fusão de dados, oferecendo eficiência operacional, embora enfrente desafios de privacidade e silos de dados. A governança exige estruturas éticas e padronização para garantir a segurança e conformidade na integração de dados heterogêneos. | M76: A IA é integrada para aprimorar a governança urbana e os serviços inteligentes em sistemas como o CIM (City Information Modeling). Os benefícios são a melhoria da eficiência na tomada de decisões e a otimização da alocação de recursos. Os principais desafios são a segurança de dados, a proteção da privacidade e a necessidade de estruturas éticas para a governança de dados urbanos. | N76: Sim | O76: Não | P76: =IF(OR(N76="",O76=""),"",IF(N76=O76,"Igual","Diferente")) -> Diferente | Q76: ChatGPT acertou ao dizer que o artigo usa Blockchain/Contratos e não técnicas de IA avançadas (NLP/ML). Gemini alucinou listando "Deep Learning/ML" como técnicas centrais, contradizendo a validação humana.
A77: 40 | B77: Journal | C77: Suíça | D77: The Development and Construction of City Information Modeling (CIM): A Survey from Data Perspective | E77: https://www.scopus.com/pages/publications/105004887982?origin=resultslist | F77: 2025 | G77: Yu, Wenya, Zhou, Xiaowei, Wang, Dongsheng, Dong, Junyu | H77: China | I77: Scopus | J77: RQ2 | K77: O artigo não emprega técnicas de IA como NLP ou ML; em vez disso, utiliza blockchain, criptografia, hashing, smart contracts e mecanismos de rastreamento para assegurar conformidade, integridade e controle de dados. A automação decorre do uso de contratos inteligentes e monitoramento distribuído. | L77: Os principais benefícios são a melhoria na eficiência operacional urbana, alocação otimizada de recursos e suporte à decisão científica baseada em dados em tempo real. Os desafios críticos incluem a proteção da privacidade, a falta de interpretabilidade ("caixa preta") dos algoritmos de IA e os altos custos computacionais para processamento em larga escala. | M77: As técnicas centrais de IA utilizadas incluem Machine Learning (ML) e Deep Learning para análise de extensos datasets urbanos, e Data Mining para oferecer insights prospectivos. Tecnologias como Reinforcement Learning (RL) e Graph Neural Networks (GNNs) estão sendo exploradas para otimização e integração de dados. Blockchain e Federated Learning (FL) são empregadas para aprimorar a segurança e a privacidade dos dados. | N77: Sim | O77: Sim | P77: =IF(OR(N77="",O77=""),"",IF(N77=O77,"Igual","Diferente")) -> Igual
A78: 40 | B78: Journal | C78: Suíça | D78: The Development and Construction of City Information Modeling (CIM): A Survey from Data Perspective | E78: https://www.scopus.com/pages/publications/105004887982?origin=resultslist | F78: 2025 | G78: Yu, Wenya, Zhou, Xiaowei, Wang, Dongsheng, Dong, Junyu | H78: China | I78: Scopus | J78: RQ3 | K78: Os benefícios apresentados incluem maior transparência, confiabilidade, detecção de anomalias, redução de manipulações e auditoria contínua. Os desafios abrangem overhead computacional, complexidade de integração entre provedores, riscos de escalabilidade e segurança em ambientes federados. | M78: Os benefícios são a melhoria da eficiência operacional, a otimização da alocação de recursos e o suporte para tomada de decisões mais precisas. Os desafios incluem a dependência de dados anotados de alta qualidade, a natureza de "caixa preta" da decisão de IA (interpretabilidade) e as severas preocupações com segurança e privacidade. | N78: Sim | O78: Sim | P78: =IF(OR(N78="",O78=""),"",IF(N78=O78,"Igual","Diferente")) -> Igual
A79: 40 | B79: Journal | C79: Suíça | D79: The Development and Construction of City Information Modeling (CIM): A Survey from Data Perspective | E79: https://www.scopus.com/pages/publications/105004887982?origin=resultslist | F79: 2025 | G79: Yu, Wenya, Zhou, Xiaowei, Wang, Dongsheng, Dong, Junyu | H79: China | I79: Scopus | J79: RQ4 | K79: A governança e ética são tratadas reforçando requisitos de rastreabilidade, verificabilidade, integridade e controles robustos de acesso, alinhados a normas de conformidade em nuvem. O framework apoia accountability e auditabilidade total do ciclo de vida dos dados em ambientes multi-cloud. | L79: Os estudos abordam a governança enfatizando a necessidade de transparência algorítmica e adesão a regulamentações como o GDPR da União Europeia para proteger dados pessoais sensíveis. Sugere-se o uso de tecnologias como Blockchain e Aprendizado Federado para garantir a segurança, rastreabilidade e conformidade ética no compartilhamento de dados. | M79: A governança é abordada pela necessidade de desenvolver estruturas éticas e aderir a regulamentações como o GDPR (Regulamento Geral de Proteção de Dados da União Europeia). A ética exige a adesão aos princípios de justiça, transparência e prestação de contas (accountability). Para a transparência, é crucial melhorar a interpretabilidade dos algoritmos de IA e utilizar tecnologias como Blockchain e Federated Learning para segurança e rastreabilidade. A LGPD brasileira não é mencionada nas fontes. | N79: Sim | O79: Sim | P79: =IF(OR(N79="",O79=""),"",IF(N79=O79,"Igual","Diferente")) -> Igual
A80: 43 | B80: Conference | C80: Portugal | D80: Using NLP and machine learning to detect data privacy violations | E80: https://www.scopus.com/pages/publications/85091537231?origin=resultslist | F80: 2020 | G80: Silva, Paulo;Goncalves, Carolina;Godinho, Carolina;Antunes, NunoCurado, Marilia | H80: Portugal | I80: Scopus | J80: RQ1 | K80: A IA é aplicada para automatizar a detecção de violações de privacidade por meio de NLP e NER, permitindo identificar e monitorar PII em textos de forma confiável, apoiando a conformidade com regulamentações como o GDPR. Os benefícios incluem automação, precisão e uso como Privacy Enhancing Technology, enquanto os desafios envolvem esforço de rotulagem, limitação de dados e risco de uso indevido. O estudo enfatiza governança baseada em transparência, código aberto e processamento efêmero. | L80: O estudo propõe o uso de Reconhecimento de Entidade Nomeada (NER) para automatizar a identificação e monitoramento de Informações Pessoalmente Identificáveis (PII), facilitando a conformidade com o GDPR. A governança emerge através do uso da ferramenta como uma Tecnologia de Aprimoramento de Privacidade (PET), oferecendo validação automatizada de dados, embora enfrente desafios significativos na obtenção de datasets rotulados para treinamento. | M80: A IA (Machine Learning e NLP) é aplicada através do Reconhecimento de Entidade Nomeada (NER) para monitorar e detectar automaticamente Informações de Identificação Pessoal (PII) em dados não estruturados, identificando potenciais violações de privacidade. Os benefícios incluem aumento da automação e confiabilidade na conformidade e a aplicação como Tecnologia de Aprimoramento de Privacidade (PET), garantindo a conformidade com o GDPR. Os principais desafios são o custo e o tempo da rotulagem manual de PII e as baixas capacidades de generalização dos modelos. | N80: Sim | O80: Sim | P80: =IF(OR(N80="",O80=""),"",IF(N80=O80,"Igual","Diferente")) -> Igual
A81: 43 | B81: Conference | C81: Portugal | D81: Using NLP and machine learning to detect data privacy violations | E81: https://www.scopus.com/pages/publications/85091537231?origin=resultslist | F81: 2020 | G81: Silva, Paulo;Goncalves, Carolina;Godinho, Carolina;Antunes, NunoCurado, Marilia | H81: Portugal | I81: Scopus | J81: RQ2 | K81: As técnicas mais utilizadas são NER e pipelines de NLP apoiados por modelos supervisionados: Naive Bayes e HMM (NLTK), Conditional Random Fields (Stanford CoreNLP) e Convolutional Neural Networks com word vectors (spaCy). Todas são empregadas para classificar entidades sensíveis em textos. | L81: O trabalho emprega Processamento de Linguagem Natural (PLN), especificamente a técnica de Reconhecimento de Entidade Nomeada (NER), utilizando ferramentas como NLTK, Stanford CoreNLP e spaCy. Os modelos de aprendizado de máquina subjacentes incluem classificadores Naive Bayes, Modelos Ocultos de Markov (HMM), Campos Aleatórios Condicionais (CRF) e Redes Neurais Convolucionais (CNNs). | M81: As técnicas centrais empregadas são o Processamento de Linguagem Natural (NLP) e sua sub-tarefa, o Reconhecimento de Entidade Nomeada (NER), para classificar PII em textos. Para treinar os modelos de Machine Learning (ML), que usam Aprendizado Supervisionado, foram utilizadas abordagens como Naive Bayes, Modelos Ocultos de Markov (HMM), Campos Aleatórios Condicionais (CRFs) e Redes Neurais Convolucionais (CNNs). Essas ferramentas permitem o monitoramento transparente e a detecção de PII para evitar violações. | N81: Sim | O81: Sim | P81: =IF(OR(N81="",O81=""),"",IF(N81=O81,"Igual","Diferente")) -> Igual
A82: 43 | B82: Conference | C82: Portugal | D82: Using NLP and machine learning to detect data privacy violations | E82: https://www.scopus.com/pages/publications/85091537231?origin=resultslist | F82: 2020 | G82: Silva, Paulo;Goncalves, Carolina;Godinho, Carolina;Antunes, NunoCurado, Marilia | H82: Portugal | I82: Scopus | J82: RQ3 | K82: Entre os principais benefícios estão alta precisão na detecção de PII, automação do monitoramento e suporte à privacidade. Os desafios citados incluem escassez de dados rotulados, alto custo de anotação manual, dificuldades de generalização e riscos de uso abusivo das ferramentas. | L82: Os benefícios citados incluem alta precisão (F1-score próximo de 90%) na detecção de dados sensíveis, automação confiável e a capacidade de validar conteúdo de dados e permissões. Os desafios envolvem o alto custo temporal para rotulagem manual de dados, a escassez de dados públicos com PII para treinamento e o risco ético da ferramenta ser usada para varreduras indevidas de dados. | M82: Os benefícios incluem o aumento da confiabilidade e automação no monitoramento de PII, atuando como Privacy Enhancing Technology (PET), e garantindo a conformidade e transparência com regulamentações. Os desafios citados são a dificuldade de obtenção de dados PII confiáveis e disponíveis publicamente, o alto custo e o tempo demandado pela rotulagem manual dos dados, e o risco de uso indevido dos mecanismos para buscas ilícitas. | N82: Sim | O82: Sim | P82: =IF(OR(N82="",O82=""),"",IF(N82=O82,"Igual","Diferente")) -> Igual
A83: 43 | B83: Conference | C83: Portugal | D83: Using NLP and machine learning to detect data privacy violations | E83: https://www.scopus.com/pages/publications/85091537231?origin=resultslist | F83: 2020 | G83: Silva, Paulo;Goncalves, Carolina;Godinho, Carolina;Antunes, NunoCurado, Marilia | H83: Portugal | I83: Scopus | J83: RQ4 | K83: Os estudos tratam governança e ética destacando a necessidade de transparência, revisão por pares via código aberto, processamento efêmero dos dados e conformidade explícita com normas como o GDPR. Há preocupação com riscos de uso inadequado que possam violar direitos de privacidade. | L83: A governança é abordada pelo alinhamento com o GDPR, promovendo a transparência através do uso de código aberto auditável e garantindo que o sistema funcione com armazenamento efêmero, descartando dados após o processamento. A ética é considerada ao desenhar o sistema como uma ferramenta de proteção (PET) que avisa usuários sobre violações, mitigando riscos de exposição de dados sensíveis. | M83: Os estudos promovem a conformidade com regulamentações de privacidade como o GDPR, enquanto a LGPD não é mencionada nas fontes. A transparência é crucial, sendo alcançada por meio de código aberto para permitir revisão, e pelo uso de armazenamento efêmero que descarta os dados após o processamento. A abordagem ética está ligada ao objetivo de proteger a privacidade e mitigar o risco de uso indevido (buscas ilegais). | N83: Sim | O83: Sim | P83: =IF(OR(N83="",O83=""),"",IF(N83=O83,"Igual","Diferente")) -> Igual
A84: 44 | B84: Conference | C84: Holanda | D84: Privacy is dead-solutions for privacy-enabled collections and use of personal health information in digital era | E84: https://www.scopus.com/pages/publications/85092439152?origin=resultslist | F84: 2020 | G84: Ruotsalainen, Pekka;Blobel, Bernd | H84: Finlandia | I84: Scopus | J84: RQ1 | K84: A IA (machine learning, algoritmos e big data analytics) é usada para coletar, processar e analisar PHI em larga escala, apoiando sistemas digitais de saúde e vigilância, mas ampliando riscos de privacidade. Os benefícios envolvem detecção precoce, suporte à saúde personalizada e eficiência. Os desafios incluem vigilância invasiva, assimetria de poder, falta de transparência e fragilidade das estruturas atuais de governança. | L84: O estudo aponta que dados de saúde são processados por algoritmos digitais e machine learning, mas a conformidade atual falha devido à tecnologia onipresente e legislação ineficaz. A governança proposta integra o conceito de "dever fiduciário de informação" com "privacidade como confiança" e o uso de smart contracts para transferir a responsabilidade de proteção para os coletores de dados | M84: A IA (Machine Learning e algoritmos) é usada para processar e compartilhar grandes volumes de Informação Pessoal de Saúde (PHI) em ecossistemas digitais. Os desafios incluem a perda de autonomia e o risco de viés/discriminação. A governança proposta combina Dever Fiduciário de Informação, Privacidade como Confiança e Contratos Inteligentes para transferir a responsabilidade da proteção para os coletores de dados. | N84: Sim | O84: Sim | P84: =IF(OR(N84="",O84=""),"",IF(N84=O84,"Igual","Diferente")) -> Igual
A85: 44 | B85: Conference | C85: Holanda | D85: Privacy is dead-solutions for privacy-enabled collections and use of personal health information in digital era | E85: https://www.scopus.com/pages/publications/85092439152?origin=resultslist | F85: 2020 | G85: Ruotsalainen, Pekka;Blobel, Bernd | H85: Finlandia | I85: Scopus | J85: RQ2 | K85: O texto menciona uso de algoritmos, big data analytics, machine learning e aplicações inteligentes para processamento e análise de PHI em ecossistemas digitais. Também cita Privacy-Enhancing Technologies (PETs), anonimização (k-anonymity, differential privacy), criptografia e auditorias como ferramentas centrais para garantir conformidade. | L85: As técnicas mencionadas incluem o uso de algoritmos de machine learning e inteligência artificial para processamento de dados em ecossistemas digitais. Para a automação da conformidade e controle de privacidade, o texto destaca especificamente o uso de smart contracts (algoritmos de computador) baseados em blockchain para validar e impor acordos digitais legalmente vinculativos. | M85: O Aprendizado de Máquina e os algoritmos digitais são utilizados para processar e analisar PHI. Para a conformidade (PET), são empregadas técnicas de proteção como criptografia, anonimização de dados (Differential privacy) e o uso de Contratos Inteligentes (algoritmos) para automatizar e validar acordos de privacidade. | N85: Sim | O85: Sim | P85: =IF(OR(N85="",O85=""),"",IF(N85=O85,"Igual","Diferente")) -> Igual
A86: 44 | B86: Conference | C86: Holanda | D86: Privacy is dead-solutions for privacy-enabled collections and use of personal health information in digital era | E86: https://www.scopus.com/pages/publications/85092439152?origin=resultslist | F86: 2020 | G86: Ruotsalainen, Pekka;Blobel, Bernd | H86: Finlandia | I86: Scopus | J86: RQ3 | K86: Benefícios: detecção antecipada, melhoria de serviços digitais, personalização e suporte à medicina 5P. Desafios: vigilância ubíqua, coleta invisível de dados, “privacy paradox”, impossibilidade prática de controle, assimetria informacional, riscos de discriminação, e fragilidade das proteções tradicionais como consentimento e políticas de privacidade. | L86: Os benefícios da solução proposta incluem transferir o ônus da proteção para o provedor, aumentar a transparência via blockchain e corrigir a assimetria de poder entre usuário e serviço. Os desafios citados são a impossibilidade de o usuário saber quais dados são coletados atualmente, a ineficácia dos modelos de consentimento e a gestão segura de chaves criptográficas. | M86: Os desafios são críticos: o uso de IA tem tornado a privacidade "quase morta" e gera assimetria de conhecimento e poder entre usuários e provedores. Isso pode levar a manipulação comportamental, discriminação e à comoditização do PHI. Os benefícios se concentram em aumentar a confiança e garantir que o uso da informação beneficie o indivíduo. | N86: Sim | O86: Sim | P86: =IF(OR(N86="",O86=""),"",IF(N86=O86,"Igual","Diferente")) -> Igual
A87: 44 | B87: Conference | C87: Holanda | D87: Privacy is dead-solutions for privacy-enabled collections and use of personal health information in digital era | E87: https://www.scopus.com/pages/publications/85092439152?origin=resultslist | F87: 2020 | G87: Ruotsalainen, Pekka;Blobel, Bernd | H87: Finlandia | I87: Scopus | J87: RQ4 | K87: A governança é abordada por meio de novos modelos como “informational fiduciary duty”, “privacy as trust”, contratos inteligentes e privacidade como propriedade. O estudo defende deveres legais de lealdade, responsabilização, monitoramento via blockchain, transparência, auditorias e regulação mais forte que vá além do consentimento do GDPR para garantir proteção real. | L87: O estudo critica o GDPR por depender do modelo de "aviso e escolha" (consentimento), considerado inadequado para ambientes virtuais distribuídos, e sugere uma lei de dever fiduciário informacional. A ética é abordada exigindo que fiduciários ajam estritamente em benefício do titular dos dados (não causando danos) e garantam transparência e prestação de contas através de trilhas de auditoria imutáveis. | M87: A governança exige a adesão a princípios como o GDPR e o CCPA, e a implementação do dever de lealdade e confidencialidade. A prestação de contas e a transparência são alcançadas através de monitoramento online e trilhas de auditoria (audit-trials) em Blockchain. A regulamentação brasileira LGPD não é mencionada nas fontes. | N87: Sim | O87: Sim | P87: =IF(OR(N87="",O87=""),"",IF(N87=O87,"Igual","Diferente")) -> Igual
A88: 52 | B88: Conference | C88: Indonésia | D88: Advancing Data Privacy in REST APIs: A Comparative Study of Machine Learning Techniques for PII Detection | E88: https://www.scopus.com/inward/record.uri?eid=2-s2.0-105012769787&doi=10.1109%2FSIML65326.2025.11081062&partnerID=40&md5=b61983e789b6880c6b305d787196d120 | F88: 2025 | G88: Sakapertana, A.S.; Faldi, W.M.; Mahardika, A.; Shiddiqi, A.M. | H88: Indonésia | I88: Scopus | J88: RQ1 | K88: A IA é aplicada para automatizar a detecção de PII em respostas de REST APIs usando modelos de machine learning (SVM e Naive Bayes) que classificam dados sensíveis em texto semi-estruturado, apoiando conformidade com GDPR e UU PDP. Os benefícios são maior segurança, qualidade do software e detecção automática de vazamentos. Os desafios incluem escassez de dados rotulados, necessidade de dados sintéticos e dificuldades em capturar a complexidade real de APIs. | L88: O estudo aplica Support Vector Machines (SVM) e Naive Bayes para detectar automaticamente Informações de Identificação Pessoal (PII) em respostas de API REST, visando a conformidade com o GDPR e a UU PDP da Indonésia. Essa integração supera métodos manuais ou baseados em regras, lidando com a natureza semi-estruturada dos dados para garantir a segurança e a qualidade do software no ciclo de vida de desenvolvimento. | M88: A IA (Support Vector Machines e Naive Bayes) é aplicada para detecção automatizada de PII em respostas de REST APIs semi-estruturadas. Os benefícios são o aprimoramento da segurança da API, qualidade do software e a garantia de conformidade com o GDPR e UU PDP. O desafio principal é a escassez de datasets rotulados reais e a dificuldade em lidar com a complexidade e a natureza semi-estruturada dos dados de API. | N88: Sim | O88: Sim | P88: =IF(OR(N88="",O88=""),"",IF(N88=O88,"Igual","Diferente")) -> Igual
A89: 52 | B89: Conference | C89: Indonésia | D89: Advancing Data Privacy in REST APIs: A Comparative Study of Machine Learning Techniques for PII Detection | E89: https://www.scopus.com/inward/record.uri?eid=2-s2.0-105012769787&doi=10.1109%2FSIML65326.2025.11081062&partnerID=40&md5=b61983e789b6880c6b305d787196d120 | F89: 2025 | G89: Sakapertana, A.S.; Faldi, W.M.; Mahardika, A.; Shiddiqi, A.M. | H89: Indonésia | I89: Scopus | J89: RQ2 | K89: As técnicas mais empregadas são SVM e Naive Bayes com extração de características via TF-IDF, aplicadas ao texto extraído de respostas JSON para classificar campos como PII, PII hasheado ou não-PII. O estudo também cita uso complementar de pré-processamento, normalização textual e geração de dados sintéticos. | L89: O trabalho emprega classificadores de Aprendizado de Máquina supervisionado, especificamente SVM e Naive Bayes, utilizando a técnica TF-IDF para extração de características em dados textuais de logs de API. O estudo também utiliza geração de dados sintéticos programáticos para criar datasets de treinamento diversificados, superando a escassez de dados rotulados reais | M89: As técnicas de IA mais empregadas são os modelos de Machine Learning de classificação multi-classe, especificamente o Support Vector Machines (SVM) e o Naive Bayes. Para a extração de características do texto (PII), é utilizado o método TF-IDF (Term Frequency-Inverse Document Frequency) para a conversão de dados textuais em vetores numéricos. | N89: Sim | O89: Sim | P89: =IF(OR(N89="",O89=""),"",IF(N89=O89,"Igual","Diferente")) -> Igual
A90: 52 | B90: Conference | C90: Indonésia | D90: Advancing Data Privacy in REST APIs: A Comparative Study of Machine Learning Techniques for PII Detection | E90: https://www.scopus.com/inward/record.uri?eid=2-s2.0-105012769787&doi=10.1109%2FSIML65326.2025.11081062&partnerID=40&md5=b61983e789b6880c6b305d787196d120 | F90: 2025 | G90: Sakapertana, A.S.; Faldi, W.M.; Mahardika, A.; Shiddiqi, A.M. | H90: Indonésia | I90: Scopus | J90: RQ3 | K90: Os principais benefícios incluem aumento da precisão na detecção de PII (SVM com F1 de 84,37%), redução de riscos de vazamento e suporte ao cumprimento regulatório. Os desafios envolvem altos índices de falsos negativos, limitação de dados reais, dificuldade em detectar PII hasheado e necessidade de modelos mais robustos para cenários reais. | L90: Os benefícios incluem alta precisão (até 90,11% com SVM) e eficiência computacional, permitindo a detecção automatizada de vazamento de dados em ambientes com recursos limitados. Os desafios citados envolvem a escassez de datasets públicos rotulados, dificuldades na detecção de PIIs em formato hash e a limitação de generalização devido ao uso de dados sintéticos. | M90: Os benefícios são o aumento da segurança de API e a capacidade de garantir a conformidade regulatória, utilizando modelos que são leves e requerem menos sobrecarga computacional em comparação com deep learning. Os desafios incluem a limitação de datasets reais rotulados, o que exige o uso de dados sintéticos, e a dificuldade dos modelos em identificar PII que foi criptografado (hashed PII). | N90: Sim | O90: Sim | P90: =IF(OR(N90="",O90=""),"",IF(N90=O90,"Igual","Diferente")) -> Igual
... A199: 127 | B199: Journal | C199: Coreia do Sul | D199: De-Identification of Facial Features in Magnetic Resonance Images: Software Development Using Deep Learning Technology | E199: https://doi.org/10.2196/22739 | F199: 2020 | G199: Yeon Uk Jeong, Soyoung Yoo, Young-Hak Kim, Woo Hyun Shim, | H199: Coreia do Sul | I199: Science Direct | J199: RQ4 | K199: Os estudos reforçam a necessidade de assegurar anonimização conforme HIPAA e GDPR, incluindo exclusão de metadados sensíveis e distorção de regiões faciais identificáveis. O artigo destaca princípios de governança como minimização de dados, responsabilidade no processamento e garantia de que imagens compartilhadas não permitam identificação, equilibrando ética, transparência e compliance. | L199: Governança e ética O trabalho aborda a governança focando na conformidade técnica com a HIPAA e o GDPR, que classificam imagens faciais reconstruídas como dados biométricos protegidos. A ética e a prestação de contas são reforçadas pela disponibilização do software como open-source ("Deface program"), permitindo que instituições protejam a identidade dos pacientes ao compartilhar repositórios de imagens. | M199: Os estudos tratam governança e ética reforçando a obrigação de remover identificadores diretos e metadados, bem como distorcer regiões faciais conforme exigido por regulamentos como HIPAA e GDPR. A abordagem privilegia transparência no processo de anonimização, responsabilidade sobre o tratamento de dados e medidas que assegurem que o compartilhamento não permita identificação do paciente. | N199: Sim | O199: Sim | P199: =IF(OR(N199="",O199=""),"",IF(N199=O199,"Igual","Diferente")) -> Igual
P200: =IF(OR(N200="",O200=""),"",IF(N200=O200,"Igual","Diferente"))
P201: =IF(OR(N201="",O201=""),"",IF(N201=O201,"Igual","Diferente"))
P202: =IF(OR(N202="",O202=""),"",IF(N202=O202,"Igual","Diferente"))
P203: =IF(OR(N203="",O203=""),"",IF(N203=O203,"Igual","Diferente"))
P204: =IF(OR(N204="",O204=""),"",IF(N204=O204,"Igual","Diferente"))
P205: =IF(OR(N205="",O205=""),"",IF(N205=O205,"Igual","Diferente"))
P206: =IF(OR(N206="",O206=""),"",IF(N206=O206,"Igual","Diferente"))
P207: =IF(OR(N207="",O207=""),"",IF(N207=O207,"Igual","Diferente"))
P208: =IF(OR(N208="",O208=""),"",IF(N208=O208,"Igual","Diferente"))
P209: =IF(OR(N209="",O209=""),"",IF(N209=O209,"Igual","Diferente"))
P210: =IF(OR(N210="",O210=""),"",IF(N210=O210,"Igual","Diferente"))
P211: =IF(OR(N211="",O211=""),"",IF(N211=O211,"Igual","Diferente"))
... P1137: =IF(OR(N1137="",O1137=""),"",IF(N1137=O1137,"Igual","Diferente"))

Sheet Métricas e Desempenho
A1: RQ | B1: Total | C1: ChatGPT – acertos % | D1: Gemini – acertos % | E1: ChatGPT – parciais (%) | F1: Gemini – parciais (%) | G1: ChatGPT – erros % | H1: Gemini – erros % | I1: Concordância
B2: =COUNTIF('Extração'!J:J,A2) -> 0 | C2: =IF(B2=0,"",COUNTIFS('Extração'!N:N,"Sim",'Extração'!J:J,A2)/B2) | D2: =IF(B2=0,"",COUNTIFS('Extração'!O:O,"Sim",'Extração'!J:J,A2)/B2) | E2: =IF(B2=0,"",COUNTIFS('Extração'!N:N,"Parcialmente",'Extração'!J:J,A2)/B2) | F2: =IF(B2=0,"",COUNTIFS('Extração'!O:O,"Parcialmente",'Extração'!J:J,A2)/B2) | G2: =IF(B2=0,"",COUNTIFS('Extração'!N:N,"Não",'Extração'!J:J,A2)/B2) | H2: =IF(B2=0,"",COUNTIFS('Extração'!O:O,"Não",'Extração'!J:J,A2)/B2) | I2: =IF(B2=0,"",COUNTIFS('Extração'!P:P,"Igual",'Extração'!J:J,A2)/B2)
B3: =COUNTIF('Extração'!J:J,A3) -> 0 | C3: =IF(B3=0,"",COUNTIFS('Extração'!N:N,"Sim",'Extração'!J:J,A3)/B3) | D3: =IF(B3=0,"",COUNTIFS('Extração'!O:O,"Sim",'Extração'!J:J,A3)/B3) | E3: =IF(B3=0,"",COUNTIFS('Extração'!N:N,"Parcialmente",'Extração'!J:J,A3)/B3) | F3: =IF(B3=0,"",COUNTIFS('Extração'!O:O,"Parcialmente",'Extração'!J:J,A3)/B3) | G3: =IF(B3=0,"",COUNTIFS('Extração'!N:N,"Não",'Extração'!J:J,A3)/B3) | H3: =IF(B3=0,"",COUNTIFS('Extração'!O:O,"Não",'Extração'!J:J,A3)/B3) | I3: =IF(B3=0,"",COUNTIFS('Extração'!P:P,"Igual",'Extração'!J:J,A3)/B3)
B4: =COUNTIF('Extração'!J:J,A4) -> 0 | C4: =IF(B4=0,"",COUNTIFS('Extração'!N:N,"Sim",'Extração'!J:J,A4)/B4) | D4: =IF(B4=0,"",COUNTIFS('Extração'!O:O,"Sim",'Extração'!J:J,A4)/B4) | E4: =IF(B4=0,"",COUNTIFS('Extração'!N:N,"Parcialmente",'Extração'!J:J,A4)/B4) | F4: =IF(B4=0,"",COUNTIFS('Extração'!O:O,"Parcialmente",'Extração'!J:J,A4)/B4) | G4: =IF(B4=0,"",COUNTIFS('Extração'!N:N,"Não",'Extração'!J:J,A4)/B4) | H4: =IF(B4=0,"",COUNTIFS('Extração'!O:O,"Não",'Extração'!J:J,A4)/B4) | I4: =IF(B4=0,"",COUNTIFS('Extração'!P:P,"Igual",'Extração'!J:J,A4)/B4)
B5: =COUNTIF('Extração'!J:J,A5) -> 0 | C5: =IF(B5=0,"",COUNTIFS('Extração'!N:N,"Sim",'Extração'!J:J,A5)/B5) | D5: =IF(B5=0,"",COUNTIFS('Extração'!O:O,"Sim",'Extração'!J:J,A5)/B5) | E5: =IF(B5=0,"",COUNTIFS('Extração'!N:N,"Parcialmente",'Extração'!J:J,A5)/B5) | F5: =IF(B5=0,"",COUNTIFS('Extração'!O:O,"Parcialmente",'Extração'!J:J,A5)/B5) | G5: =IF(B5=0,"",COUNTIFS('Extração'!N:N,"Não",'Extração'!J:J,A5)/B5) | H5: =IF(B5=0,"",COUNTIFS('Extração'!O:O,"Não",'Extração'!J:J,A5)/B5) | I5: =IF(B5=0,"",COUNTIFS('Extração'!P:P,"Igual",'Extração'!J:J,A5)/B5)
B6: =COUNTIF('Extração'!J:J,A6) -> 0 | C6: =IF(B6=0,"",COUNTIFS('Extração'!N:N,"Sim",'Extração'!J:J,A6)/B6) | D6: =IF(B6=0,"",COUNTIFS('Extração'!O:O,"Sim",'Extração'!J:J,A6)/B6) | E6: =IF(B6=0,"",COUNTIFS('Extração'!N:N,"Parcialmente",'Extração'!J:J,A6)/B6) | F6: =IF(B6=0,"",COUNTIFS('Extração'!O:O,"Parcialmente",'Extração'!J:J,A6)/B6) | G6: =IF(B6=0,"",COUNTIFS('Extração'!N:N,"Não",'Extração'!J:J,A6)/B6) | H6: =IF(B6=0,"",COUNTIFS('Extração'!O:O,"Não",'Extração'!J:J,A6)/B6) | I6: =IF(B6=0,"",COUNTIFS('Extração'!P:P,"Igual",'Extração'!J:J,A6)/B6)
B7: =COUNTIF('Extração'!J:J,A7) -> 0 | C7: =IF(B7=0,"",COUNTIFS('Extração'!N:N,"Sim",'Extração'!J:J,A7)/B7) | D7: =IF(B7=0,"",COUNTIFS('Extração'!O:O,"Sim",'Extração'!J:J,A7)/B7) | E7: =IF(B7=0,"",COUNTIFS('Extração'!N:N,"Parcialmente",'Extração'!J:J,A7)/B7) | F7: =IF(B7=0,"",COUNTIFS('Extração'!O:O,"Parcialmente",'Extração'!J:J,A7)/B7) | G7: =IF(B7=0,"",COUNTIFS('Extração'!N:N,"Não",'Extração'!J:J,A7)/B7) | H7: =IF(B7=0,"",COUNTIFS('Extração'!O:O,"Não",'Extração'!J:J,A7)/B7) | I7: =IF(B7=0,"",COUNTIFS('Extração'!P:P,"Igual",'Extração'!J:J,A7)/B7)
B8: =COUNTIF('Extração'!J:J,A8) -> 0 | C8: =IF(B8=0,"",COUNTIFS('Extração'!N:N,"Sim",'Extração'!J:J,A8)/B8) | D8: =IF(B8=0,"",COUNTIFS('Extração'!O:O,"Sim",'Extração'!J:J,A8)/B8) | E8: =IF(B8=0,"",COUNTIFS('Extração'!N:N,"Parcialmente",'Extração'!J:J,A8)/B8) | F8: =IF(B8=0,"",COUNTIFS('Extração'!O:O,"Parcialmente",'Extração'!J:J,A8)/B8) | G8: =IF(B8=0,"",COUNTIFS('Extração'!N:N,"Não",'Extração'!J:J,A8)/B8) | H8: =IF(B8=0,"",COUNTIFS('Extração'!O:O,"Não",'Extração'!J:J,A8)/B8) | I8: =IF(B8=0,"",COUNTIFS('Extração'!P:P,"Igual",'Extração'!J:J,A8)/B8)
B9: =COUNTIF('Extração'!J:J,A9) -> 0 | C9: =IF(B9=0,"",COUNTIFS('Extração'!N:N,"Sim",'Extração'!J:J,A9)/B9) | D9: =IF(B9=0,"",COUNTIFS('Extração'!O:O,"Sim",'Extração'!J:J,A9)/B9) | E9: =IF(B9=0,"",COUNTIFS('Extração'!N:N,"Parcialmente",'Extração'!J:J,A9)/B9) | F9: =IF(B9=0,"",COUNTIFS('Extração'!O:O,"Parcialmente",'Extração'!J:J,A9)/B9) | G9: =IF(B9=0,"",COUNTIFS('Extração'!N:N,"Não",'Extração'!J:J,A9)/B9) | H9: =IF(B9=0,"",COUNTIFS('Extração'!O:O,"Não",'Extração'!J:J,A9)/B9) | I9: =IF(B9=0,"",COUNTIFS('Extração'!P:P,"Igual",'Extração'!J:J,A9)/B9)
B10: =COUNTIF('Extração'!J:J,A10) -> 0 | C10: =IF(B10=0,"",COUNTIFS('Extração'!N:N,"Sim",'Extração'!J:J,A10)/B10) | D10: =IF(B10=0,"",COUNTIFS('Extração'!O:O,"Sim",'Extração'!J:J,A10)/B10) | E10: =IF(B10=0,"",COUNTIFS('Extração'!N:N,"Parcialmente",'Extração'!J:J,A10)/B10) | F10: =IF(B10=0,"",COUNTIFS('Extração'!O:O,"Parcialmente",'Extração'!J:J,A10)/B10) | G10: =IF(B10=0,"",COUNTIFS('Extração'!N:N,"Não",'Extração'!J:J,A10)/B10) | H10: =IF(B10=0,"",COUNTIFS('Extração'!O:O,"Não",'Extração'!J:J,A10)/B10) | I10: =IF(B10=0,"",COUNTIFS('Extração'!P:P,"Igual",'Extração'!J:J,A10)/B10)
B11: =COUNTIF('Extração'!J:J,A11) -> 0 | C11: =IF(B11=0,"",COUNTIFS('Extração'!N:N,"Sim",'Extração'!J:J,A11)/B11) | D11: =IF(B11=0,"",COUNTIFS('Extração'!O:O,"Sim",'Extração'!J:J,A11)/B11) | E11: =IF(B11=0,"",COUNTIFS('Extração'!N:N,"Parcialmente",'Extração'!J:J,A11)/B11) | F11: =IF(B11=0,"",COUNTIFS('Extração'!O:O,"Parcialmente",'Extração'!J:J,A11)/B11) | G11: =IF(B11=0,"",COUNTIFS('Extração'!N:N,"Não",'Extração'!J:J,A11)/B11) | H11: =IF(B11=0,"",COUNTIFS('Extração'!O:O,"Não",'Extração'!J:J,A11)/B11) | I11: =IF(B11=0,"",COUNTIFS('Extração'!P:P,"Igual",'Extração'!J:J,A11)/B11)
B12: =COUNTIF('Extração'!J:J,A12) -> 0 | C12: =IF(B12=0,"",COUNTIFS('Extração'!N:N,"Sim",'Extração'!J:J,A12)/B12) | D12: =IF(B12=0,"",COUNTIFS('Extração'!O:O,"Sim",'Extração'!J:J,A12)/B12) | E12: =IF(B12=0,"",COUNTIFS('Extração'!N:N,"Parcialmente",'Extração'!J:J,A12)/B12) | F12: =IF(B12=0,"",COUNTIFS('Extração'!O:O,"Parcialmente",'Extração'!J:J,A12)/B12) | G12: =IF(B12=0,"",COUNTIFS('Extração'!N:N,"Não",'Extração'!J:J,A12)/B12) | H12: =IF(B12=0,"",COUNTIFS('Extração'!O:O,"Não",'Extração'!J:J,A12)/B12) | I12: =IF(B12=0,"",COUNTIFS('Extração'!P:P,"Igual",'Extração'!J:J,A12)/B12)
B13: =COUNTIF('Extração'!J:J,A13) -> 0 | C13: =IF(B13=0,"",COUNTIFS('Extração'!N:N,"Sim",'Extração'!J:J,A13)/B13) | D13: =IF(B13=0,"",COUNTIFS('Extração'!O:O,"Sim",'Extração'!J:J,A13)/B13) | E13: =IF(B13=0,"",COUNTIFS('Extração'!N:N,"Parcialmente",'Extração'!J:J,A13)/B13) | F13: =IF(B13=0,"",COUNTIFS('Extração'!O:O,"Parcialmente",'Extração'!J:J,A13)/B13) | G13: =IF(B13=0,"",COUNTIFS('Extração'!N:N,"Não",'Extração'!J:J,A13)/B13) | H13: =IF(B13=0,"",COUNTIFS('Extração'!O:O,"Não",'Extração'!J:J,A13)/B13) | I13: =IF(B13=0,"",COUNTIFS('Extração'!P:P,"Igual",'Extração'!J:J,A13)/B13)
... B1000: =COUNTIF('Extração'!J:J,A1000) -> 0 | C1000: =IF(B1000=0,"",COUNTIFS('Extração'!N:N,"Sim",'Extração'!J:J,A1000)/B1000) | D1000: =IF(B1000=0,"",COUNTIFS('Extração'!O:O,"Sim",'Extração'!J:J,A1000)/B1000) | E1000: =IF(B1000=0,"",COUNTIFS('Extração'!N:N,"Parcialmente",'Extração'!J:J,A1000)/B1000) | F1000: =IF(B1000=0,"",COUNTIFS('Extração'!O:O,"Parcialmente",'Extração'!J:J,A1000)/B1000) | G1000: =IF(B1000=0,"",COUNTIFS('Extração'!N:N,"Não",'Extração'!J:J,A1000)/B1000) | H1000: =IF(B1000=0,"",COUNTIFS('Extração'!O:O,"Não",'Extração'!J:J,A1000)/B1000) | I1000: =IF(B1000=0,"",COUNTIFS('Extração'!P:P,"Igual",'Extração'!J:J,A1000)/B1000)
